[
  {
    "type": "RECEIVE",
    "datetime": "2023-10-02 09:07 PM",
    "amount": 700,
    "name": "LA*****E M.",
    "mobile": "09481296881",
    "msg": null,
    "balance": 83000.5,
    "reference": "4012426394876",
    "wallet": "09156467832",
    "duty": "mrbrown",
    "num": 159,
    "id": 158864,
    "note": ""
  },
  {
    "type": "RECEIVE",
    "datetime": "2023-10-02 09:07 PM",
    "amount": 200,
    "name": "JA*N AN***O C.",
    "mobile": "09958966897",
    "msg": "4564",
    "balance": 82300.5,
    "reference": "3012426381884",
    "wallet": "09156467832",
    "duty": "mrbrown",
    "num": 158,
    "id": 158865,
    "note": ""
  },
  {
    "type": "RECEIVE",
    "datetime": "2023-10-02 08:50 PM",
    "amount": 250,
    "name": "L** M.",
    "mobile": "09483205843",
    "msg": null,
    "balance": 72243.5,
    "reference": "1012426037033",
    "wallet": "09156467832",
    "duty": "lovely",
    "num": 157,
    "id": 158835,
    "note": ""
  },
  {
    "type": "RECEIVE",
    "datetime": "2023-10-02 08:50 PM",
    "amount": 495,
    "name": "JO*N CH********R G.",
    "mobile": "09453959991",
    "msg": null,
    "balance": 71993.5,
    "reference": "7012426033386",
    "wallet": "09156467832",
    "duty": "lovely",
    "num": 156,
    "id": 158843,
    "note": ""
  },
  {
    "type": "RECEIVE",
    "datetime": "2023-10-02 08:50 PM",
    "amount": 120,
    "name": "AL***N T.",
    "mobile": "09363137826",
    "msg": null,
    "balance": 71498.5,
    "reference": "9012426031594",
    "wallet": "09156467832",
    "duty": "lovely",
    "num": 155,
    "id": 158837,
    "note": ""
  },
  {
    "type": "RECEIVE",
    "datetime": "2023-10-02 08:50 PM",
    "amount": 200,
    "name": "CY***L B.",
    "mobile": "09503359421",
    "msg": "2140",
    "balance": 71378.5,
    "reference": "6012426031239",
    "wallet": "09156467832",
    "duty": "lovely",
    "num": 154,
    "id": 158842,
    "note": ""
  },
  {
    "type": "RECEIVE",
    "datetime": "2023-10-02 08:49 PM",
    "amount": 500,
    "name": "JA***N A.",
    "mobile": "09150298335",
    "msg": null,
    "balance": 71178.5,
    "reference": "6012426028735",
    "wallet": "09156467832",
    "duty": "lovely",
    "num": 153,
    "id": 158832,
    "note": ""
  },
  {
    "type": "RECEIVE",
    "datetime": "2023-10-02 08:49 PM",
    "amount": 150,
    "name": "DA***N P.",
    "mobile": "09608960420",
    "msg": null,
    "balance": 68508.5,
    "reference": "1012426011732",
    "wallet": "09156467832",
    "duty": "lovely",
    "num": 152,
    "id": 158831,
    "note": ""
  },
  {
    "type": "RECEIVE",
    "datetime": "2023-10-02 08:49 PM",
    "amount": 1270,
    "name": "AN***L N.",
    "mobile": "09278126905",
    "msg": "5492",
    "balance": 70678.5,
    "reference": "5012426021001",
    "wallet": "09156467832",
    "duty": "lovely",
    "num": 151,
    "id": 158833,
    "note": ""
  },
  {
    "type": "RECEIVE",
    "datetime": "2023-10-02 08:49 PM",
    "amount": 900,
    "name": "RI****D N.",
    "mobile": "09603813767",
    "msg": null,
    "balance": 69408.5,
    "reference": "5012426012093",
    "wallet": "09156467832",
    "duty": "lovely",
    "num": 150,
    "id": 158826,
    "note": ""
  },
  {
    "type": "RECEIVE",
    "datetime": "2023-10-02 08:49 PM",
    "amount": 1000,
    "name": "JE***D H.",
    "mobile": "09458811200",
    "msg": "7962",
    "balance": 68358.5,
    "reference": "9012426000048",
    "wallet": "09156467832",
    "duty": "lovely",
    "num": 149,
    "id": 158819,
    "note": ""
  },
  {
    "type": "RECEIVE",
    "datetime": "2023-10-02 08:49 PM",
    "amount": 100,
    "name": "JO*O D.",
    "mobile": "09750856221",
    "msg": null,
    "balance": 67358.5,
    "reference": "1012426010398",
    "wallet": "09156467832",
    "duty": "lovely",
    "num": 148,
    "id": 158827,
    "note": ""
  },
  {
    "type": "RECEIVE",
    "datetime": "2023-10-02 08:48 PM",
    "amount": 150,
    "name": "GE*****O J** M.",
    "mobile": "09266320879",
    "msg": null,
    "balance": 66758.5,
    "reference": "6012426007670",
    "wallet": "09156467832",
    "duty": "lovely",
    "num": 147,
    "id": 158828,
    "note": ""
  },
  {
    "type": "RECEIVE",
    "datetime": "2023-10-02 08:48 PM",
    "amount": 500,
    "name": "JO*N BR**N A.",
    "mobile": "09563986049",
    "msg": "yes",
    "balance": 67258.5,
    "reference": "4012426009828",
    "wallet": "09156467832",
    "duty": "lovely",
    "num": 146,
    "id": 158820,
    "note": ""
  },
  {
    "type": "RECEIVE",
    "datetime": "2023-10-02 08:48 PM",
    "amount": 200,
    "name": "DE***S F.",
    "mobile": "09203894442",
    "msg": null,
    "balance": 66608.5,
    "reference": "4012426005666",
    "wallet": "09156467832",
    "duty": "lovely",
    "num": 145,
    "id": 158811,
    "note": ""
  },
  {
    "type": "RECEIVE",
    "datetime": "2023-10-02 08:48 PM",
    "amount": 119,
    "name": "JO**N A.",
    "mobile": "09054328851",
    "msg": null,
    "balance": 66408.5,
    "reference": "1012426003447",
    "wallet": "09156467832",
    "duty": "lovely",
    "num": 144,
    "id": 158821,
    "note": ""
  },
  {
    "type": "RECEIVE",
    "datetime": "2023-10-02 08:48 PM",
    "amount": 500,
    "name": "RE*****O J* P.",
    "mobile": "09618009132",
    "msg": null,
    "balance": 65789.5,
    "reference": "5012426000163",
    "wallet": "09156467832",
    "duty": "lovely",
    "num": 143,
    "id": 158822,
    "note": ""
  },
  {
    "type": "RECEIVE",
    "datetime": "2023-10-02 08:48 PM",
    "amount": 500,
    "name": "JA***E R.",
    "mobile": "09568547775",
    "msg": "ok",
    "balance": 66289.5,
    "reference": "3012426001616",
    "wallet": "09156467832",
    "duty": "lovely",
    "num": 142,
    "id": 158815,
    "note": ""
  },
  {
    "type": "RECEIVE",
    "datetime": "2023-10-02 08:48 PM",
    "amount": 500,
    "name": "KE**N J.",
    "mobile": "09939897748",
    "msg": null,
    "balance": 65289.5,
    "reference": "5012425997908",
    "wallet": "09156467832",
    "duty": "lovely",
    "num": 141,
    "id": 158818,
    "note": ""
  },
  {
    "type": "RECEIVE",
    "datetime": "2023-10-02 08:48 PM",
    "amount": 500,
    "name": "AL**N E.",
    "mobile": "09466707035",
    "msg": null,
    "balance": 64789.5,
    "reference": "2012425996677",
    "wallet": "09156467832",
    "duty": "lovely",
    "num": 140,
    "id": 158813,
    "note": ""
  },
  {
    "type": "RECEIVE",
    "datetime": "2023-10-02 08:50 PM",
    "amount": 100,
    "name": "JO*N RI**E L.",
    "mobile": "09634327169",
    "msg": "babawi lang ako",
    "balance": 72343.5,
    "reference": "2012426041987",
    "wallet": "09156467832",
    "duty": "lovely",
    "num": 139,
    "id": 158838,
    "note": ""
  },
  {
    "type": "RECEIVE",
    "datetime": "2023-10-02 08:50 PM",
    "amount": 500,
    "name": "M* M.",
    "mobile": "09053278521",
    "msg": "pa cash in",
    "balance": 72843.5,
    "reference": "1012426042605",
    "wallet": "09156467832",
    "duty": "lovely",
    "num": 138,
    "id": 158836,
    "note": ""
  },
  {
    "type": "RECEIVE",
    "datetime": "2023-10-02 08:50 PM",
    "amount": 140,
    "name": "DE****E D.",
    "mobile": "09354517531",
    "msg": null,
    "balance": 72983.5,
    "reference": "3012426042920",
    "wallet": "09156467832",
    "duty": "lovely",
    "num": 137,
    "id": 158823,
    "note": ""
  },
  {
    "type": "RECEIVE",
    "datetime": "2023-10-02 08:50 PM",
    "amount": 200,
    "name": "MA**™*C D.",
    "mobile": "09976940709",
    "msg": "6967",
    "balance": 73183.5,
    "reference": "1012426043243",
    "wallet": "09156467832",
    "duty": "lovely",
    "num": 136,
    "id": 158847,
    "note": ""
  },
  {
    "type": "RECEIVE",
    "datetime": "2023-10-02 08:50 PM",
    "amount": 100,
    "name": "JI**Y A.",
    "mobile": "09351612016",
    "msg": null,
    "balance": 73283.5,
    "reference": "1012426043604",
    "wallet": "09156467832",
    "duty": "lovely",
    "num": 135,
    "id": "",
    "note": "no_request"
  },
  {
    "type": "RECEIVE",
    "datetime": "2023-10-02 08:50 PM",
    "amount": 300,
    "name": "VI***R U.",
    "mobile": "09239831584",
    "msg": null,
    "balance": 73583.5,
    "reference": "4012426045104",
    "wallet": "09156467832",
    "duty": "lovely",
    "num": 134,
    "id": 158846,
    "note": ""
  },
  {
    "type": "RECEIVE",
    "datetime": "2023-10-02 08:50 PM",
    "amount": 150,
    "name": "FL*******A M.",
    "mobile": "09333636835",
    "msg": null,
    "balance": 73733.5,
    "reference": "9012426049460",
    "wallet": "09156467832",
    "duty": "lovely",
    "num": 133,
    "id": 158830,
    "note": ""
  },
  {
    "type": "RECEIVE",
    "datetime": "2023-10-02 08:51 PM",
    "amount": 980,
    "name": "AG****O I** M.",
    "mobile": "09919312064",
    "msg": "5713",
    "balance": 74813.5,
    "reference": "0012426053273",
    "wallet": "09156467832",
    "duty": "lovely",
    "num": 132,
    "id": 158850,
    "note": ""
  },
  {
    "type": "RECEIVE",
    "datetime": "2023-10-02 08:51 PM",
    "amount": 100,
    "name": "EF**N J* D.",
    "mobile": "09915813738",
    "msg": "8729",
    "balance": 73833.5,
    "reference": "0012426053009",
    "wallet": "09156467832",
    "duty": "lovely",
    "num": 131,
    "id": 158853,
    "note": ""
  },
  {
    "type": "RECEIVE",
    "datetime": "2023-10-02 08:51 PM",
    "amount": 100,
    "name": "FR***E S.",
    "mobile": "09489098870",
    "msg": null,
    "balance": 75100.5,
    "reference": "2012426060719",
    "wallet": "09156467832",
    "duty": "lovely",
    "num": 130,
    "id": 158849,
    "note": ""
  },
  {
    "type": "RECEIVE",
    "datetime": "2023-10-02 08:51 PM",
    "amount": 187,
    "name": "JO*L T.",
    "mobile": "09185582162",
    "msg": null,
    "balance": 75000.5,
    "reference": "3012426054226",
    "wallet": "09156467832",
    "duty": "lovely",
    "num": 129,
    "id": 158852,
    "note": ""
  },
  {
    "type": "RECEIVE",
    "datetime": "2023-10-02 08:51 PM",
    "amount": 100,
    "name": "WI****T C.",
    "mobile": "09154545870",
    "msg": "7229",
    "balance": 75200.5,
    "reference": "1012426068966",
    "wallet": "09156467832",
    "duty": "lovely",
    "num": 128,
    "id": 158804,
    "note": ""
  },
  {
    "type": "RECEIVE",
    "datetime": "2023-10-02 08:51 PM",
    "amount": 400,
    "name": "LE****D C.",
    "mobile": "09632970446",
    "msg": null,
    "balance": 75600.5,
    "reference": "0012426069281",
    "wallet": "09156467832",
    "duty": "lovely",
    "num": 127,
    "id": 158851,
    "note": ""
  },
  {
    "type": "RECEIVE",
    "datetime": "2023-10-02 08:51 PM",
    "amount": 300,
    "name": "AN***O C.",
    "mobile": "09927686341",
    "msg": null,
    "balance": 75900.5,
    "reference": "8012426071527",
    "wallet": "09156467832",
    "duty": "lovely",
    "num": 126,
    "id": 158841,
    "note": ""
  },
  {
    "type": "RECEIVE",
    "datetime": "2023-10-02 08:52 PM",
    "amount": 1000,
    "name": "JO***Y M.",
    "mobile": "09163161915",
    "msg": null,
    "balance": 76900.5,
    "reference": "2012426072239",
    "wallet": "09156467832",
    "duty": "lovely",
    "num": 125,
    "id": 158859,
    "note": ""
  },
  {
    "type": "RECEIVE",
    "datetime": "2023-10-02 08:52 PM",
    "amount": 5000,
    "name": "JU***T D.",
    "mobile": "09424420896",
    "msg": null,
    "balance": 81900.5,
    "reference": "3012426086459",
    "wallet": "09156467832",
    "duty": "lovely",
    "num": 124,
    "id": 158856,
    "note": ""
  },
  {
    "type": "RECEIVE",
    "datetime": "2023-10-02 08:52 PM",
    "amount": 200,
    "name": "JE***K P.",
    "mobile": "09266170737",
    "msg": "6388",
    "balance": 82100.5,
    "reference": "8012426088237",
    "wallet": "09156467832",
    "duty": "lovely",
    "num": 123,
    "id": 158858,
    "note": ""
  },
  {
    "type": "RECEIVE",
    "datetime": "2023-10-02 08:48 PM",
    "amount": 150,
    "name": "VI****E V.",
    "mobile": "09753442184",
    "msg": "4995",
    "balance": 64289.5,
    "reference": "2012425995572",
    "wallet": "09156467832",
    "duty": "lovely",
    "num": 122,
    "id": 158816,
    "note": ""
  },
  {
    "type": "RECEIVE",
    "datetime": "2023-10-02 08:48 PM",
    "amount": 200,
    "name": "CH******N M.",
    "mobile": "09166529250",
    "msg": null,
    "balance": 64139.5,
    "reference": "9012425995069",
    "wallet": "09156467832",
    "duty": "lovely",
    "num": 121,
    "id": 158808,
    "note": ""
  },
  {
    "type": "RECEIVE",
    "datetime": "2023-10-02 08:48 PM",
    "amount": 2000,
    "name": "MA*K JO***H CH******N D.",
    "mobile": "09275542847",
    "msg": "3979",
    "balance": null,
    "reference": "1012425994517",
    "wallet": "09156467832",
    "duty": "lovely",
    "num": 120,
    "id": 158810,
    "note": ""
  },
  {
    "type": "RECEIVE",
    "datetime": "2023-10-02 08:48 PM",
    "amount": 500,
    "name": "HA***L PA**O M.",
    "mobile": "09163874877",
    "msg": "2749",
    "balance": 61939.5,
    "reference": "7012425994283",
    "wallet": "09156467832",
    "duty": "lovely",
    "num": 119,
    "id": 158812,
    "note": ""
  },
  {
    "type": "RECEIVE",
    "datetime": "2023-10-02 08:48 PM",
    "amount": 100,
    "name": "AR******E |* A.",
    "mobile": "09919154579",
    "msg": "2064",
    "balance": null,
    "reference": "8012425993972",
    "wallet": "09156467832",
    "duty": "lovely",
    "num": 118,
    "id": 158807,
    "note": ""
  },
  {
    "type": "RECEIVE",
    "datetime": "2023-10-02 08:48 PM",
    "amount": 141,
    "name": "RU*Y S.",
    "mobile": "09154321505",
    "msg": null,
    "balance": 61339.5,
    "reference": "9012425990702",
    "wallet": "09156467832",
    "duty": "lovely",
    "num": 117,
    "id": 158809,
    "note": ""
  },
  {
    "type": "RECEIVE",
    "datetime": "2023-10-02 08:47 PM",
    "amount": 200,
    "name": "JO***“A M.",
    "mobile": "09273115660",
    "msg": null,
    "balance": 61198.5,
    "reference": "6012425985173",
    "wallet": "09156467832",
    "duty": "lovely",
    "num": 116,
    "id": 158814,
    "note": ""
  },
  {
    "type": "RECEIVE",
    "datetime": "2023-10-02 08:47 PM",
    "amount": 100,
    "name": "MA**Y A.",
    "mobile": "09154812602",
    "msg": null,
    "balance": 60998.5,
    "reference": "2012425983154",
    "wallet": "09156467832",
    "duty": "lovely",
    "num": 115,
    "id": 158805,
    "note": ""
  },
  {
    "type": "RECEIVE",
    "datetime": "2023-10-02 08:24 PM",
    "amount": 100,
    "name": "JU***N A.",
    "mobile": "09913089289",
    "msg": "7785 ",
    "balance": 60898.5,
    "reference": "8012425487080",
    "wallet": "09156467832",
    "duty": "lovely",
    "num": 114,
    "id": 158679,
    "note": ""
  },
  {
    "type": "RECEIVE",
    "datetime": "2023-10-02 08:24 PM",
    "amount": 800,
    "name": "ED***N B.",
    "mobile": "09091592623",
    "msg": "4341",
    "balance": 60798.5,
    "reference": "6012425483254",
    "wallet": "09156467832",
    "duty": "lovely",
    "num": 113,
    "id": 158799,
    "note": ""
  },
  {
    "type": "RECEIVE",
    "datetime": "2023-10-02 08:24 PM",
    "amount": 1000,
    "name": "M* LU****N G.",
    "mobile": "09298856243",
    "msg": null,
    "balance": 59998.5,
    "reference": "6012425468124",
    "wallet": "09156467832",
    "duty": "lovely",
    "num": 112,
    "id": 158735,
    "note": ""
  },
  {
    "type": "RECEIVE",
    "datetime": "2023-10-02 08:23 PM",
    "amount": 320,
    "name": "AR****E A.",
    "mobile": "09530597892",
    "msg": "2180",
    "balance": 58998.5,
    "reference": "4012425458620",
    "wallet": "09156467832",
    "duty": "lovely",
    "num": 111,
    "id": 158798,
    "note": ""
  },
  {
    "type": "RECEIVE",
    "datetime": "2023-10-02 08:23 PM",
    "amount": 150,
    "name": "GI*A D.",
    "mobile": "09072622188",
    "msg": "4622",
    "balance": 58678.5,
    "reference": "5012425458423",
    "wallet": "09156467832",
    "duty": "lovely",
    "num": 110,
    "id": 158801,
    "note": ""
  },
  {
    "type": "RECEIVE",
    "datetime": "2023-10-02 08:23 PM",
    "amount": 150,
    "name": "LI*****O G.",
    "mobile": "09701954219",
    "msg": null,
    "balance": 58528.5,
    "reference": "5012425449712",
    "wallet": "09156467832",
    "duty": "lovely",
    "num": 109,
    "id": 158797,
    "note": ""
  },
  {
    "type": "RECEIVE",
    "datetime": "2023-10-02 08:23 PM",
    "amount": 240,
    "name": "M** P.",
    "mobile": "09919225491",
    "msg": null,
    "balance": 58378.5,
    "reference": "9012425448175",
    "wallet": "09156467832",
    "duty": "lovely",
    "num": 108,
    "id": 158784,
    "note": ""
  },
  {
    "type": "RECEIVE",
    "datetime": "2023-10-02 08:23 PM",
    "amount": 1000,
    "name": "MA*C. BR**N M.",
    "mobile": "09959156010",
    "msg": null,
    "balance": 58138.5,
    "reference": "8012425444656",
    "wallet": "09156467832",
    "duty": "lovely",
    "num": 107,
    "id": 158789,
    "note": ""
  },
  {
    "type": "RECEIVE",
    "datetime": "2023-10-02 08:22 PM",
    "amount": 177,
    "name": "HI****T A.",
    "mobile": "09567164807",
    "msg": "9084",
    "balance": 55138.5,
    "reference": "5012425442472",
    "wallet": "09156467832",
    "duty": "lovely",
    "num": 106,
    "id": 158794,
    "note": ""
  },
  {
    "type": "RECEIVE",
    "datetime": "2023-10-02 08:22 PM",
    "amount": 471,
    "name": "JO*N ER*C F.",
    "mobile": "09269187965",
    "msg": null,
    "balance": 38561.5,
    "reference": "9012425434445",
    "wallet": "09156467832",
    "duty": "lovely",
    "num": 105,
    "id": 158779,
    "note": ""
  },
  {
    "type": "RECEIVE",
    "datetime": "2023-10-02 08:22 PM",
    "amount": 297,
    "name": "JO*N AM**L A.",
    "mobile": "09395276862",
    "msg": "5574",
    "balance": 37247.5,
    "reference": "6012425425244",
    "wallet": "09156467832",
    "duty": "lovely",
    "num": 104,
    "id": 158787,
    "note": ""
  },
  {
    "type": "RECEIVE",
    "datetime": "2023-10-02 08:22 PM",
    "amount": 100,
    "name": "PR******O D.",
    "mobile": "09168231135",
    "msg": "3126",
    "balance": 38961.5,
    "reference": "6012425438536",
    "wallet": "09156467832",
    "duty": "lovely",
    "num": 103,
    "id": 158796,
    "note": ""
  },
  {
    "type": "RECEIVE",
    "datetime": "2023-10-02 08:22 PM",
    "amount": 200,
    "name": "HA*™*L PA**O M.",
    "mobile": "09163874877",
    "msg": "4012",
    "balance": 38090.5,
    "reference": "7012425431660",
    "wallet": "09156467832",
    "duty": "lovely",
    "num": 102,
    "id": 158791,
    "note": ""
  },
  {
    "type": "RECEIVE",
    "datetime": "2023-10-02 08:22 PM",
    "amount": 200,
    "name": "LL™*D C.",
    "mobile": "09457502920",
    "msg": "credit ",
    "balance": 37890.5,
    "reference": "4012425430282",
    "wallet": "09156467832",
    "duty": "lovely",
    "num": 101,
    "id": 158729,
    "note": ""
  },
  {
    "type": "RECEIVE",
    "datetime": "2023-10-02 08:22 PM",
    "amount": 300,
    "name": "AR**N KA*L M.",
    "mobile": "09089145346",
    "msg": null,
    "balance": 38861.5,
    "reference": "2012425434915",
    "wallet": "09156467832",
    "duty": "lovely",
    "num": 100,
    "id": 158783,
    "note": ""
  },
  {
    "type": "RECEIVE",
    "datetime": "2023-10-02 08:22 PM",
    "amount": 443,
    "name": "AL****H M.",
    "mobile": "09106210771",
    "msg": "2910",
    "balance": 37690.5,
    "reference": "7012425427798",
    "wallet": "09156467832",
    "duty": "lovely",
    "num": 99,
    "id": 158788,
    "note": ""
  },
  {
    "type": "RECEIVE",
    "datetime": "2023-10-02 08:21 PM",
    "amount": 130,
    "name": "MA*K AN***O P.",
    "mobile": "09566525719",
    "msg": "cash in",
    "balance": 36950.5,
    "reference": "8012425420522",
    "wallet": "09156467832",
    "duty": "lovely",
    "num": 98,
    "id": 158754,
    "note": ""
  },
  {
    "type": "RECEIVE",
    "datetime": "2023-10-02 08:21 PM",
    "amount": 350,
    "name": "RO™**O R.",
    "mobile": "09564515390",
    "msg": "7008",
    "balance": 36820.5,
    "reference": "7012425416064",
    "wallet": "09156467832",
    "duty": "lovely",
    "num": 97,
    "id": 158771,
    "note": ""
  },
  {
    "type": "RECEIVE",
    "datetime": "2023-10-02 08:21 PM",
    "amount": 320,
    "name": "RE*A JA*E P.",
    "mobile": "09915114250",
    "msg": null,
    "balance": 36470.5,
    "reference": "7012425413472",
    "wallet": "09156467832",
    "duty": "lovely",
    "num": 96,
    "id": 158781,
    "note": ""
  },
  {
    "type": "RECEIVE",
    "datetime": "2023-10-02 08:21 PM",
    "amount": 198,
    "name": "MY***N S.",
    "mobile": "09668419093",
    "msg": null,
    "balance": 36050.5,
    "reference": "3012425409631",
    "wallet": "09156467832",
    "duty": "lovely",
    "num": 95,
    "id": 158746,
    "note": ""
  },
  {
    "type": "RECEIVE",
    "datetime": "2023-10-02 08:21 PM",
    "amount": 100,
    "name": "MI*E AN**E Q.",
    "mobile": "09354671615",
    "msg": null,
    "balance": 36150.5,
    "reference": "5012425409972",
    "wallet": "09156467832",
    "duty": "lovely",
    "num": 94,
    "id": 158780,
    "note": ""
  },
  {
    "type": "RECEIVE",
    "datetime": "2023-10-02 08:21 PM",
    "amount": 500,
    "name": "EF**N N.",
    "mobile": "09569976667",
    "msg": "6803",
    "balance": 35852.5,
    "reference": "5012425405812",
    "wallet": "09156467832",
    "duty": "lovely",
    "num": 93,
    "id": 158767,
    "note": ""
  },
  {
    "type": "RECEIVE",
    "datetime": "2023-10-02 08:21 PM",
    "amount": 100,
    "name": "RI*****N P.",
    "mobile": "09669563991",
    "msg": null,
    "balance": 35352.5,
    "reference": "7012425404514",
    "wallet": "09156467832",
    "duty": "lovely",
    "num": 92,
    "id": 158777,
    "note": ""
  },
  {
    "type": "RECEIVE",
    "datetime": "2023-10-02 08:21 PM",
    "amount": 100,
    "name": "RA**Y S.",
    "mobile": "09159877183",
    "msg": "4083",
    "balance": 35252.5,
    "reference": "0012425400157",
    "wallet": "09156467832",
    "duty": "lovely",
    "num": 91,
    "id": 158762,
    "note": ""
  },
  {
    "type": "RECEIVE",
    "datetime": "2023-10-02 08:20 PM",
    "amount": 300,
    "name": "MA*****H B.",
    "mobile": "09484800356",
    "msg": null,
    "balance": 35152.5,
    "reference": "5012425388108",
    "wallet": "09156467832",
    "duty": "lovely",
    "num": 90,
    "id": 158766,
    "note": ""
  },
  {
    "type": "RECEIVE",
    "datetime": "2023-10-02 08:20 PM",
    "amount": 150,
    "name": "LE****N J** P.",
    "mobile": "09472624048",
    "msg": "6227",
    "balance": 34852.5,
    "reference": "0012425384024",
    "wallet": "09156467832",
    "duty": "lovely",
    "num": 89,
    "id": 158760,
    "note": ""
  },
  {
    "type": "RECEIVE",
    "datetime": "2023-10-02 08:20 PM",
    "amount": 100,
    "name": "JA**S NI***E B.",
    "mobile": "09617134414",
    "msg": null,
    "balance": 34702.5,
    "reference": "9012425382810",
    "wallet": "09156467832",
    "duty": "lovely",
    "num": 88,
    "id": 158755,
    "note": ""
  },
  {
    "type": "RECEIVE",
    "datetime": "2023-10-02 08:20 PM",
    "amount": 300,
    "name": "CE***O C.",
    "mobile": "09270517392",
    "msg": null,
    "balance": 34602.5,
    "reference": "3012425378645",
    "wallet": "09156467832",
    "duty": "lovely",
    "num": 87,
    "id": 158747,
    "note": ""
  },
  {
    "type": "RECEIVE",
    "datetime": "2023-10-02 08:20 PM",
    "amount": 800,
    "name": "FR******K R.",
    "mobile": "09451801013",
    "msg": null,
    "balance": 34302.5,
    "reference": "7012425377176",
    "wallet": "09156467832",
    "duty": "lovely",
    "num": 86,
    "id": 158759,
    "note": ""
  },
  {
    "type": "RECEIVE",
    "datetime": "2023-10-02 08:19 PM",
    "amount": 1000,
    "name": "AV“*L SH**Y A.",
    "mobile": "09708162017",
    "msg": null,
    "balance": 33302.5,
    "reference": "5012425374567",
    "wallet": "09156467832",
    "duty": "lovely",
    "num": 85,
    "id": "",
    "note": "no_request"
  },
  {
    "type": "RECEIVE",
    "datetime": "2023-10-02 08:19 PM",
    "amount": 100,
    "name": "RE*****O J* S.",
    "mobile": "09971536624",
    "msg": null,
    "balance": 32302.5,
    "reference": "2012425368958",
    "wallet": "09156467832",
    "duty": "lovely",
    "num": 84,
    "id": 158751,
    "note": ""
  },
  {
    "type": "RECEIVE",
    "datetime": "2023-10-02 08:19 PM",
    "amount": 200,
    "name": "RO***D B.",
    "mobile": "09532540039",
    "msg": null,
    "balance": 32202.5,
    "reference": "1012425368780",
    "wallet": "09156467832",
    "duty": "lovely",
    "num": 83,
    "id": 158743,
    "note": ""
  },
  {
    "type": "RECEIVE",
    "datetime": "2023-10-02 08:19 PM",
    "amount": 1500,
    "name": "RE“****N J.",
    "mobile": "09501469835",
    "msg": "6882",
    "balance": 32002.5,
    "reference": "7012425363481",
    "wallet": "09156467832",
    "duty": "lovely",
    "num": 82,
    "id": 158731,
    "note": ""
  },
  {
    "type": "RECEIVE",
    "datetime": "2023-10-02 08:19 PM",
    "amount": 100,
    "name": "SA’*T VI****T D.",
    "mobile": "09451231006",
    "msg": null,
    "balance": 30502.5,
    "reference": "2012425361021",
    "wallet": "09156467832",
    "duty": "lovely",
    "num": 81,
    "id": 158748,
    "note": ""
  },
  {
    "type": "RECEIVE",
    "datetime": "2023-10-02 08:19 PM",
    "amount": 200,
    "name": "DU****E A** B.",
    "mobile": "09126346602",
    "msg": null,
    "balance": 30402.5,
    "reference": "1012425355226",
    "wallet": "09156467832",
    "duty": "lovely",
    "num": 80,
    "id": 158737,
    "note": ""
  },
  {
    "type": "RECEIVE",
    "datetime": "2023-10-02 08:22 PM",
    "amount": 2000,
    "name": "JAN N.",
    "mobile": "09567621147",
    "msg": "7197",
    "balance": 57138.5,
    "reference": "4012425443121",
    "wallet": "09156467832",
    "duty": "lovely",
    "num": 79,
    "id": "",
    "note": ""
  },
  {
    "type": "RECEIVE",
    "datetime": "2023-10-02 08:22 PM",
    "amount": 16000,
    "name": "RY*N R.",
    "mobile": "09772583308",
    "msg": null,
    "balance": 54961.5,
    "reference": "5012425441178",
    "wallet": "09156467832",
    "duty": "lovely",
    "num": 78,
    "id": 158795,
    "note": ""
  },
  {
    "type": "RECEIVE",
    "datetime": "2023-10-02 08:18 PM",
    "amount": 750,
    "name": "RO***T V** M.",
    "mobile": "09380037372",
    "msg": "6570",
    "balance": 30202.5,
    "reference": "4012425352511",
    "wallet": "09156467832",
    "duty": "lovely",
    "num": 77,
    "id": 158744,
    "note": ""
  },
  {
    "type": "RECEIVE",
    "datetime": "2023-10-02 08:18 PM",
    "amount": 100,
    "name": "PE*****L C.",
    "mobile": "09455290591",
    "msg": null,
    "balance": 29452.5,
    "reference": "6012425349726",
    "wallet": "09156467832",
    "duty": "lovely",
    "num": 76,
    "id": 158739,
    "note": ""
  },
  {
    "type": "RECEIVE",
    "datetime": "2023-10-02 08:18 PM",
    "amount": 104,
    "name": "JO***Y M.",
    "mobile": "09608233174",
    "msg": null,
    "balance": 29352.5,
    "reference": "7012425348653",
    "wallet": "09156467832",
    "duty": "lovely",
    "num": 75,
    "id": 158741,
    "note": ""
  },
  {
    "type": "RECEIVE",
    "datetime": "2023-10-02 08:18 PM",
    "amount": 500,
    "name": "RO*™**O G.",
    "mobile": "09756736108",
    "msg": null,
    "balance": 29248.5,
    "reference": "7012425347203",
    "wallet": "09156467832",
    "duty": "lovely",
    "num": 74,
    "id": 158733,
    "note": ""
  },
  {
    "type": "RECEIVE",
    "datetime": "2023-10-02 08:18 PM",
    "amount": 500,
    "name": "PE**O JA****R C.",
    "mobile": "09761093115",
    "msg": null,
    "balance": 28748.5,
    "reference": "4012425342150",
    "wallet": "09156467832",
    "duty": "lovely",
    "num": 73,
    "id": 158738,
    "note": ""
  },
  {
    "type": "RECEIVE",
    "datetime": "2023-10-02 08:18 PM",
    "amount": 300,
    "name": "MA***N P.",
    "mobile": "09301898321",
    "msg": "9971",
    "balance": 28248.5,
    "reference": "1012425339302",
    "wallet": "09156467832",
    "duty": "lovely",
    "num": 72,
    "id": 158727,
    "note": ""
  },
  {
    "type": "RECEIVE",
    "datetime": "2023-10-02 08:18 PM",
    "amount": 100,
    "name": "M* LY“***R M.",
    "mobile": "09488126805",
    "msg": null,
    "balance": 27448.5,
    "reference": "0012425333514",
    "wallet": "09156467832",
    "duty": "lovely",
    "num": 71,
    "id": 158724,
    "note": ""
  },
  {
    "type": "RECEIVE",
    "datetime": "2023-10-02 08:18 PM",
    "amount": 200,
    "name": "L** MA*K C.",
    "mobile": "09512533938",
    "msg": null,
    "balance": 27948.5,
    "reference": "3012425337768",
    "wallet": "09156467832",
    "duty": "lovely",
    "num": 70,
    "id": 158697,
    "note": ""
  },
  {
    "type": "RECEIVE",
    "datetime": "2023-10-02 08:18 PM",
    "amount": 300,
    "name": "RE*****E S.",
    "mobile": "09178547008",
    "msg": null,
    "balance": 27748.5,
    "reference": "8012425334289",
    "wallet": "09156467832",
    "duty": "lovely",
    "num": 69,
    "id": 158736,
    "note": ""
  },
  {
    "type": "RECEIVE",
    "datetime": "2023-10-02 08:18 PM",
    "amount": 500,
    "name": "LU****O H.",
    "mobile": "09971870319",
    "msg": null,
    "balance": 27348.5,
    "reference": "9012425332923",
    "wallet": "09156467832",
    "duty": "lovely",
    "num": 68,
    "id": 158732,
    "note": ""
  },
  {
    "type": "RECEIVE",
    "datetime": "2023-10-02 08:20 PM",
    "amount": 200,
    "name": "MA*K BR**N S.",
    "mobile": "09076028980",
    "msg": null,
    "balance": 33502.5,
    "reference": "4012425375700",
    "wallet": "09156467832",
    "duty": "lovely",
    "num": 67,
    "id": 158714,
    "note": ""
  },
  {
    "type": "RECEIVE",
    "datetime": "2023-10-02 08:17 PM",
    "amount": 100,
    "name": "LU*S R.",
    "mobile": "09271167448",
    "msg": null,
    "balance": 26348.5,
    "reference": "2012425327722",
    "wallet": "09156467832",
    "duty": "lovely",
    "num": 66,
    "id": 158725,
    "note": ""
  },
  {
    "type": "RECEIVE",
    "datetime": "2023-10-02 08:17 PM",
    "amount": 500,
    "name": "ED*E A.",
    "mobile": "09564974838",
    "msg": "09564974838 sender",
    "balance": 26848.5,
    "reference": "0012425329396",
    "wallet": "09156467832",
    "duty": "lovely",
    "num": 65,
    "id": 158716,
    "note": ""
  },
  {
    "type": "RECEIVE",
    "datetime": "2023-10-02 08:17 PM",
    "amount": 700,
    "name": "DE**E AN*E M.",
    "mobile": "09971736021",
    "msg": "6697",
    "balance": 26248.5,
    "reference": "0012425325702",
    "wallet": "09156467832",
    "duty": "lovely",
    "num": 64,
    "id": 158720,
    "note": ""
  },
  {
    "type": "RECEIVE",
    "datetime": "2023-10-02 08:17 PM",
    "amount": 500,
    "name": "DAO E.",
    "mobile": "09121392431",
    "msg": null,
    "balance": 25548.5,
    "reference": "7012425324651",
    "wallet": "09156467832",
    "duty": "lovely",
    "num": 63,
    "id": 158721,
    "note": ""
  },
  {
    "type": "RECEIVE",
    "datetime": "2023-10-02 08:17 PM",
    "amount": 100,
    "name": "CL**Y N.",
    "mobile": "09852648711",
    "msg": null,
    "balance": 25048.5,
    "reference": "7012425324179",
    "wallet": "09156467832",
    "duty": "lovely",
    "num": 62,
    "id": "",
    "note": "no_request"
  },
  {
    "type": "RECEIVE",
    "datetime": "2023-10-02 08:17 PM",
    "amount": 100,
    "name": "R** Z.",
    "mobile": "09812994493",
    "msg": null,
    "balance": 24948.5,
    "reference": "9012425321270",
    "wallet": "09156467832",
    "duty": "lovely",
    "num": 61,
    "id": 158722,
    "note": ""
  },
  {
    "type": "RECEIVE",
    "datetime": "2023-10-02 08:17 PM",
    "amount": 300,
    "name": "JE***E D.",
    "mobile": "09976731458",
    "msg": null,
    "balance": 24348.5,
    "reference": "5012425317280",
    "wallet": "09156467832",
    "duty": "lovely",
    "num": 60,
    "id": 158717,
    "note": ""
  },
  {
    "type": "RECEIVE",
    "datetime": "2023-10-02 08:17 PM",
    "amount": 500,
    "name": "LL******N ER**K P.",
    "mobile": "09777201364",
    "msg": null,
    "balance": 24848.5,
    "reference": "9012425317826",
    "wallet": "09156467832",
    "duty": "lovely",
    "num": 59,
    "id": 158715,
    "note": ""
  },
  {
    "type": "RECEIVE",
    "datetime": "2023-10-02 08:16 PM",
    "amount": 200,
    "name": "RO*L S.",
    "mobile": "09166550917",
    "msg": null,
    "balance": 24048.5,
    "reference": "4012425304173",
    "wallet": "09156467832",
    "duty": "lovely",
    "num": 58,
    "id": 158719,
    "note": ""
  },
  {
    "type": "RECEIVE",
    "datetime": "2023-10-02 08:16 PM",
    "amount": 500,
    "name": "CA™****A C.",
    "mobile": "09366648449",
    "msg": null,
    "balance": 23748.5,
    "reference": "3012425302582",
    "wallet": "09156467832",
    "duty": "lovely",
    "num": 57,
    "id": 158706,
    "note": ""
  },
  {
    "type": "RECEIVE",
    "datetime": "2023-10-02 08:16 PM",
    "amount": 100,
    "name": "MA*K LE***R G.",
    "mobile": "09608661217",
    "msg": null,
    "balance": 23848.5,
    "reference": "4012425302774",
    "wallet": "09156467832",
    "duty": "lovely",
    "num": 56,
    "id": 158709,
    "note": ""
  },
  {
    "type": "RECEIVE",
    "datetime": "2023-10-02 08:16 PM",
    "amount": 1000,
    "name": "RA**N M.",
    "mobile": "09672549125",
    "msg": "9741",
    "balance": 23248.5,
    "reference": "2012425300400",
    "wallet": "09156467832",
    "duty": "lovely",
    "num": 55,
    "id": 158710,
    "note": ""
  },
  {
    "type": "RECEIVE",
    "datetime": "2023-10-02 08:16 PM",
    "amount": 100,
    "name": "WI***N V.",
    "mobile": "09958749500",
    "msg": "3754",
    "balance": 22148.5,
    "reference": "6012425293201",
    "wallet": "09156467832",
    "duty": "lovely",
    "num": 54,
    "id": 158695,
    "note": ""
  },
  {
    "type": "RECEIVE",
    "datetime": "2023-10-02 08:16 PM",
    "amount": 100,
    "name": "JE****Y J.",
    "mobile": "09357939088",
    "msg": null,
    "balance": 22248.5,
    "reference": "6012425295512",
    "wallet": "09156467832",
    "duty": "lovely",
    "num": 53,
    "id": 158712,
    "note": ""
  },
  {
    "type": "RECEIVE",
    "datetime": "2023-10-02 08:15 PM",
    "amount": 801,
    "name": "JE***D H.",
    "mobile": "09458811200",
    "msg": "8821",
    "balance": 20548.5,
    "reference": "9012425276908",
    "wallet": "09156467832",
    "duty": "lovely",
    "num": 52,
    "id": 158696,
    "note": ""
  },
  {
    "type": "RECEIVE",
    "datetime": "2023-10-02 08:15 PM",
    "amount": 500,
    "name": "MA*K KE**N J** T.",
    "mobile": "09156490696",
    "msg": null,
    "balance": 22048.5,
    "reference": "1012425281593",
    "wallet": "09156467832",
    "duty": "lovely",
    "num": 51,
    "id": 158701,
    "note": ""
  },
  {
    "type": "RECEIVE",
    "datetime": "2023-10-02 08:15 PM",
    "amount": 1000,
    "name": "J** R** P.",
    "mobile": "09604713816",
    "msg": null,
    "balance": 21548.5,
    "reference": "8012425277163",
    "wallet": "09156467832",
    "duty": "lovely",
    "num": 50,
    "id": 158704,
    "note": ""
  },
  {
    "type": "RECEIVE",
    "datetime": "2023-10-02 08:15 PM",
    "amount": 300,
    "name": "EM*****L A.",
    "mobile": "09635205512",
    "msg": "2053",
    "balance": 19747.5,
    "reference": "2012425276191",
    "wallet": "09156467832",
    "duty": "lovely",
    "num": 49,
    "id": 158702,
    "note": ""
  },
  {
    "type": "RECEIVE",
    "datetime": "2023-10-02 08:15 PM",
    "amount": 200,
    "name": "AR***E M.",
    "mobile": "09284610178",
    "msg": null,
    "balance": 19447.5,
    "reference": "8012425275388",
    "wallet": "09156467832",
    "duty": "lovely",
    "num": 48,
    "id": 158703,
    "note": ""
  },
  {
    "type": "RECEIVE",
    "datetime": "2023-10-02 08:15 PM",
    "amount": 500,
    "name": "LOA M.",
    "mobile": "09194102147",
    "msg": "2261",
    "balance": 17277.5,
    "reference": "0012425263240",
    "wallet": "09156467832",
    "duty": "lovely",
    "num": 47,
    "id": 158687,
    "note": ""
  },
  {
    "type": "RECEIVE",
    "datetime": "2023-10-02 08:15 PM",
    "amount": 500,
    "name": "RA™*L P.",
    "mobile": "09673843325",
    "msg": null,
    "balance": null,
    "reference": "6012425273401",
    "wallet": "09156467832",
    "duty": "lovely",
    "num": 46,
    "id": 158698,
    "note": ""
  },
  {
    "type": "RECEIVE",
    "datetime": "2023-10-02 08:15 PM",
    "amount": 200,
    "name": "RE*****O I.",
    "mobile": "09104006843",
    "msg": "7849",
    "balance": 18747.5,
    "reference": "1012425272218",
    "wallet": "09156467832",
    "duty": "lovely",
    "num": 45,
    "id": 158699,
    "note": ""
  },
  {
    "type": "RECEIVE",
    "datetime": "2023-10-02 08:15 PM",
    "amount": 300,
    "name": "DA***O M.",
    "mobile": "09534024683",
    "msg": null,
    "balance": 18547.5,
    "reference": "0012425266858",
    "wallet": "09156467832",
    "duty": "lovely",
    "num": 44,
    "id": 158694,
    "note": ""
  },
  {
    "type": "RECEIVE",
    "datetime": "2023-10-02 08:15 PM",
    "amount": 100,
    "name": "EL***T S.",
    "mobile": "09296901683",
    "msg": null,
    "balance": null,
    "reference": "0012425265272",
    "wallet": "09156467832",
    "duty": "lovely",
    "num": 43,
    "id": 158700,
    "note": ""
  },
  {
    "type": "RECEIVE",
    "datetime": "2023-10-02 08:15 PM",
    "amount": 170,
    "name": "ED**N L.",
    "mobile": "09157348892",
    "msg": "3528",
    "balance": 18147.5,
    "reference": "5012425264043",
    "wallet": "09156467832",
    "duty": "lovely",
    "num": 42,
    "id": 158690,
    "note": ""
  },
  {
    "type": "RECEIVE",
    "datetime": "2023-10-02 08:15 PM",
    "amount": 700,
    "name": "DI*O C.",
    "mobile": "09218696209",
    "msg": null,
    "balance": null,
    "reference": "9012425263385",
    "wallet": "09156467832",
    "duty": "lovely",
    "num": 41,
    "id": 158686,
    "note": ""
  },
  {
    "type": "RECEIVE",
    "datetime": "2023-10-02 08:14 PM",
    "amount": 190,
    "name": "AN****O T.",
    "mobile": "09650690219",
    "msg": null,
    "balance": 16777.5,
    "reference": "3012425257633",
    "wallet": "09156467832",
    "duty": "lovely",
    "num": 40,
    "id": 158693,
    "note": ""
  },
  {
    "type": "RECEIVE",
    "datetime": "2023-10-02 08:05 PM",
    "amount": 500,
    "name": "AL**N E.",
    "mobile": "09466707035",
    "msg": null,
    "balance": 15632.5,
    "reference": "2012425052936",
    "wallet": "09156467832",
    "duty": "lovely",
    "num": 39,
    "id": 158657,
    "note": ""
  },
  {
    "type": "RECEIVE",
    "datetime": "2023-10-02 08:06 PM",
    "amount": 155,
    "name": "MA**A RU*H F.",
    "mobile": "09076491880",
    "msg": "thank you po",
    "balance": 16487.5,
    "reference": "6012425073790",
    "wallet": "09156467832",
    "duty": "lovely",
    "num": 38,
    "id": 158672,
    "note": ""
  },
  {
    "type": "RECEIVE",
    "datetime": "2023-10-02 08:07 PM",
    "amount": 100,
    "name": "JO*O D.",
    "mobile": "09750856221",
    "msg": null,
    "balance": 16587.5,
    "reference": "1012425082013",
    "wallet": "09156467832",
    "duty": "lovely",
    "num": 37,
    "id": 158682,
    "note": ""
  },
  {
    "type": "RECEIVE",
    "datetime": "2023-10-02 08:06 PM",
    "amount": 200,
    "name": "RA**Y H.",
    "mobile": "09678294072",
    "msg": "1551",
    "balance": 16332.5,
    "reference": "5012425070085",
    "wallet": "09156467832",
    "duty": "lovely",
    "num": 36,
    "id": 158671,
    "note": ""
  },
  {
    "type": "RECEIVE",
    "datetime": "2023-10-02 08:06 PM",
    "amount": 200,
    "name": "SA**H JA*E L.",
    "mobile": "09958347840",
    "msg": null,
    "balance": 16132.5,
    "reference": "5012425060439",
    "wallet": "09156467832",
    "duty": "lovely",
    "num": 35,
    "id": 158673,
    "note": ""
  },
  {
    "type": "RECEIVE",
    "datetime": "2023-10-02 08:06 PM",
    "amount": 100,
    "name": "AL**H M** E.",
    "mobile": "09756753449",
    "msg": null,
    "balance": 15932.5,
    "reference": "7012425059282",
    "wallet": "09156467832",
    "duty": "lovely",
    "num": 34,
    "id": 158674,
    "note": ""
  },
  {
    "type": "RECEIVE",
    "datetime": "2023-10-02 08:06 PM",
    "amount": 200,
    "name": "AL**N A.",
    "mobile": "09659470466",
    "msg": null,
    "balance": 15832.5,
    "reference": "2012425055028",
    "wallet": "09156467832",
    "duty": "lovely",
    "num": 33,
    "id": 158669,
    "note": ""
  },
  {
    "type": "RECEIVE",
    "datetime": "2023-10-02 08:05 PM",
    "amount": 350,
    "name": "IS**C. J* T.",
    "mobile": "09618878703",
    "msg": "payment ",
    "balance": 13655.5,
    "reference": "1012425048777",
    "wallet": "09156467832",
    "duty": "lovely",
    "num": 32,
    "id": 158670,
    "note": ""
  },
  {
    "type": "RECEIVE",
    "datetime": "2023-10-02 08:05 PM",
    "amount": 500,
    "name": "RA****D D.",
    "mobile": "09661338071",
    "msg": null,
    "balance": 13305.5,
    "reference": "3012425047239",
    "wallet": "09156467832",
    "duty": "lovely",
    "num": 31,
    "id": 158659,
    "note": ""
  },
  {
    "type": "RECEIVE",
    "datetime": "2023-10-02 08:05 PM",
    "amount": 1477,
    "name": "NI***N GED S.",
    "mobile": "09668254968",
    "msg": "3338",
    "balance": 15132.5,
    "reference": "8012425048995",
    "wallet": "09156467832",
    "duty": "lovely",
    "num": 30,
    "id": 158665,
    "note": ""
  },
  {
    "type": "RECEIVE",
    "datetime": "2023-10-02 08:05 PM",
    "amount": 3000,
    "name": "KI*G JO*N O.",
    "mobile": "09817230887",
    "msg": "8336",
    "balance": 12705.5,
    "reference": "0012425044833",
    "wallet": "09156467832",
    "duty": "lovely",
    "num": 29,
    "id": 158667,
    "note": ""
  },
  {
    "type": "RECEIVE",
    "datetime": "2023-10-02 08:05 PM",
    "amount": 100,
    "name": "EM*****L D.",
    "mobile": "09272558305",
    "msg": "6521",
    "balance": 12805.5,
    "reference": "4012425046038",
    "wallet": "09156467832",
    "duty": "lovely",
    "num": 28,
    "id": 158663,
    "note": ""
  },
  {
    "type": "RECEIVE",
    "datetime": "2023-10-02 08:05 PM",
    "amount": 200,
    "name": "JO****E VI*Z L.",
    "mobile": "09068131097",
    "msg": "1026",
    "balance": 9705.5,
    "reference": "4012425040580",
    "wallet": "09156467832",
    "duty": "lovely",
    "num": 27,
    "id": 158666,
    "note": ""
  },
  {
    "type": "RECEIVE",
    "datetime": "2023-10-02 08:05 PM",
    "amount": 100,
    "name": "AL**N A.",
    "mobile": "09168201499",
    "msg": null,
    "balance": 9505.5,
    "reference": "5012425033671",
    "wallet": "09156467832",
    "duty": "lovely",
    "num": 26,
    "id": 158652,
    "note": ""
  },
  {
    "type": "RECEIVE",
    "datetime": "2023-10-02 08:04 PM",
    "amount": 204,
    "name": "GU******O P.",
    "mobile": "09311014106",
    "msg": "cash inn",
    "balance": 9405.5,
    "reference": "0012425031875",
    "wallet": "09156467832",
    "duty": "lovely",
    "num": 25,
    "id": 158649,
    "note": ""
  },
  {
    "type": "RECEIVE",
    "datetime": "2023-10-02 08:04 PM",
    "amount": 2000,
    "name": "MA*O E.",
    "mobile": "09694932375",
    "msg": "8030",
    "balance": 9201.5,
    "reference": "1012425030207",
    "wallet": "09156467832",
    "duty": "lovely",
    "num": 24,
    "id": 158661,
    "note": ""
  },
  {
    "type": "RECEIVE",
    "datetime": "2023-10-02 08:04 PM",
    "amount": 150,
    "name": "DE***R U.",
    "mobile": "09067259169",
    "msg": null,
    "balance": 6201.5,
    "reference": "9012425011886",
    "wallet": "09156467832",
    "duty": "lovely",
    "num": 23,
    "id": 158637,
    "note": ""
  },
  {
    "type": "RECEIVE",
    "datetime": "2023-10-02 08:04 PM",
    "amount": 350,
    "name": "HA™*S P.",
    "mobile": "09955170274",
    "msg": null,
    "balance": 7201.5,
    "reference": "1012425027945",
    "wallet": "09156467832",
    "duty": "lovely",
    "num": 22,
    "id": 158645,
    "note": ""
  },
  {
    "type": "RECEIVE",
    "datetime": "2023-10-02 08:04 PM",
    "amount": 100,
    "name": "JE*******N G.",
    "mobile": "09385688718",
    "msg": null,
    "balance": 6851.5,
    "reference": "6012425018920",
    "wallet": "09156467832",
    "duty": "lovely",
    "num": 21,
    "id": 158647,
    "note": ""
  },
  {
    "type": "RECEIVE",
    "datetime": "2023-10-02 08:04 PM",
    "amount": 400,
    "name": "WE*****N P.",
    "mobile": "09157422415",
    "msg": null,
    "balance": 6751.5,
    "reference": "5012425014929",
    "wallet": "09156467832",
    "duty": "lovely",
    "num": 20,
    "id": 158651,
    "note": ""
  },
  {
    "type": "RECEIVE",
    "datetime": "2023-10-02 08:04 PM",
    "amount": 150,
    "name": "CH***Y M.",
    "mobile": "09063619467",
    "msg": "7745",
    "balance": 6351.5,
    "reference": "0012425012792",
    "wallet": "09156467832",
    "duty": "lovely",
    "num": 19,
    "id": 158648,
    "note": ""
  },
  {
    "type": "RECEIVE",
    "datetime": "2023-10-02 08:04 PM",
    "amount": 100,
    "name": "JO*L A.",
    "mobile": "09308180022",
    "msg": null,
    "balance": 6051.5,
    "reference": "5012425011196",
    "wallet": "09156467832",
    "duty": "lovely",
    "num": 18,
    "id": 158638,
    "note": ""
  },
  {
    "type": "RECEIVE",
    "datetime": "2023-10-02 08:04 PM",
    "amount": 186,
    "name": "JU****E G.",
    "mobile": "09363171186",
    "msg": null,
    "balance": 5951.5,
    "reference": "1012425009769",
    "wallet": "09156467832",
    "duty": "lovely",
    "num": 17,
    "id": 158643,
    "note": ""
  },
  {
    "type": "RECEIVE",
    "datetime": "2023-10-02 08:03 PM",
    "amount": 300,
    "name": "JA***N M.",
    "mobile": "09664419244",
    "msg": null,
    "balance": 5765.5,
    "reference": "5012425007439",
    "wallet": "09156467832",
    "duty": "lovely",
    "num": 16,
    "id": 158629,
    "note": ""
  },
  {
    "type": "RECEIVE",
    "datetime": "2023-10-02 08:03 PM",
    "amount": 100,
    "name": "FR****S A.",
    "mobile": "09384612533",
    "msg": "1209",
    "balance": 5465.5,
    "reference": "1012425001678",
    "wallet": "09156467832",
    "duty": "lovely",
    "num": 15,
    "id": 158641,
    "note": ""
  },
  {
    "type": "RECEIVE",
    "datetime": "2023-10-02 08:03 PM",
    "amount": 100,
    "name": "MA****L B.",
    "mobile": "09124214899",
    "msg": "9802",
    "balance": 5365.5,
    "reference": "8012424998945",
    "wallet": "09156467832",
    "duty": "lovely",
    "num": 14,
    "id": 158633,
    "note": ""
  },
  {
    "type": "RECEIVE",
    "datetime": "2023-10-02 08:03 PM",
    "amount": 100,
    "name": "JO*N RI**E L.",
    "mobile": "09634327169",
    "msg": null,
    "balance": 5265.5,
    "reference": "2012424997092",
    "wallet": "09156467832",
    "duty": "lovely",
    "num": 13,
    "id": 158630,
    "note": ""
  },
  {
    "type": "RECEIVE",
    "datetime": "2023-10-02 08:03 PM",
    "amount": 300,
    "name": "HA*™*L PA**O M.",
    "mobile": "09163874877",
    "msg": "6858",
    "balance": 5165.5,
    "reference": "7012424995728",
    "wallet": "09156467832",
    "duty": "lovely",
    "num": 12,
    "id": 158644,
    "note": ""
  },
  {
    "type": "RECEIVE",
    "datetime": "2023-10-02 08:03 PM",
    "amount": 1500,
    "name": "JO*N BR**N A.",
    "mobile": "09563986049",
    "msg": "padaga kam",
    "balance": 4865.5,
    "reference": "4012424992882",
    "wallet": "09156467832",
    "duty": "lovely",
    "num": 11,
    "id": 158623,
    "note": ""
  },
  {
    "type": "RECEIVE",
    "datetime": "2023-10-02 08:03 PM",
    "amount": 200,
    "name": "RA**Y S.",
    "mobile": "09159877183",
    "msg": "3475",
    "balance": 3365.5,
    "reference": "0012424991098",
    "wallet": "09156467832",
    "duty": "lovely",
    "num": 10,
    "id": 158632,
    "note": ""
  },
  {
    "type": "RECEIVE",
    "datetime": "2023-10-02 08:03 PM",
    "amount": 100,
    "name": "JO****E VI*Z L.",
    "mobile": "09068131097",
    "msg": "9298",
    "balance": 3065.5,
    "reference": "4012424989640",
    "wallet": "09156467832",
    "duty": "lovely",
    "num": 9,
    "id": 158640,
    "note": ""
  },
  {
    "type": "RECEIVE",
    "datetime": "2023-10-02 08:03 PM",
    "amount": 100,
    "name": "VI****E A.",
    "mobile": "09690201834",
    "msg": "4209",
    "balance": 3165.5,
    "reference": "6012424990410",
    "wallet": "09156467832",
    "duty": "lovely",
    "num": 8,
    "id": 158634,
    "note": ""
  },
  {
    "type": "RECEIVE",
    "datetime": "2023-10-02 08:03 PM",
    "amount": 110,
    "name": "DE****E D.",
    "mobile": "09354517531",
    "msg": null,
    "balance": 2965.5,
    "reference": "3012424987812",
    "wallet": "09156467832",
    "duty": "lovely",
    "num": 7,
    "id": 158625,
    "note": ""
  },
  {
    "type": "RECEIVE",
    "datetime": "2023-10-02 08:03 PM",
    "amount": 100,
    "name": "NI*O B.",
    "mobile": "09954900166",
    "msg": null,
    "balance": 2855.5,
    "reference": "3012424986477",
    "wallet": "09156467832",
    "duty": "lovely",
    "num": 6,
    "id": 158628,
    "note": ""
  },
  {
    "type": "RECEIVE",
    "datetime": "2023-10-02 08:03 PM",
    "amount": 105,
    "name": "KE**N R.",
    "mobile": "09454176236",
    "msg": "9639",
    "balance": 2755.5,
    "reference": "7012424985652",
    "wallet": "09156467832",
    "duty": "lovely",
    "num": 5,
    "id": 158635,
    "note": ""
  },
  {
    "type": "RECEIVE",
    "datetime": "2023-10-02 08:02 PM",
    "amount": 300,
    "name": "AN****N P.",
    "mobile": "09558903138",
    "msg": null,
    "balance": 2650.5,
    "reference": "2012424983309",
    "wallet": "09156467832",
    "duty": "lovely",
    "num": 4,
    "id": 158626,
    "note": ""
  },
  {
    "type": "RECEIVE",
    "datetime": "2023-10-02 08:02 PM",
    "amount": 1250,
    "name": "KE**N K.",
    "mobile": "09978628692",
    "msg": "1487",
    "balance": 2350.5,
    "reference": "3012424980795",
    "wallet": "09156467832",
    "duty": "lovely",
    "num": 3,
    "id": 158627,
    "note": ""
  },
  {
    "type": "RECEIVE",
    "datetime": "2023-10-02 08:01 PM",
    "amount": 900,
    "name": "WI****L R.",
    "mobile": "09974033791",
    "msg": null,
    "balance": 1100.5,
    "reference": "7012424958272",
    "wallet": "09156467832",
    "duty": "lovely",
    "num": 2,
    "id": 158624,
    "note": ""
  },
  {
    "type": "RECEIVE",
    "datetime": "2023-10-01 04:42 AM",
    "amount": 200,
    "name": "MA**O J* M.",
    "mobile": "09999850874",
    "msg": null,
    "balance": 200.5,
    "reference": "8012386137178",
    "wallet": "09156467832",
    "duty": "lovely",
    "num": 1,
    "id": "",
    "note": "no_request"
  }
]