[
  {
    "type": "RECEIVE",
    "datetime": "2023-09-24 08:45 PM",
    "amount": 200,
    "name": "RH**L I** R.",
    "mobile": "09353434080",
    "msg": "cashin",
    "balance": 82083,
    "reference": "1012258722671",
    "wallet": "09055033688",
    "duty": "jahn",
    "num": 235,
    "id": 109632,
    "note": ""
  },
  {
    "type": "RECEIVE",
    "datetime": "2023-09-24 08:43 PM",
    "amount": 100,
    "name": "KO****N GR**E A.",
    "mobile": "09218366194",
    "msg": "hiyang",
    "balance": 81883,
    "reference": "8012258684402",
    "wallet": "09055033688",
    "duty": "jahn",
    "num": 234,
    "id": 109622,
    "note": ""
  },
  {
    "type": "RECEIVE",
    "datetime": "2023-09-24 08:37 PM",
    "amount": 100,
    "name": "AM*R S.",
    "mobile": "09300243936",
    "msg": null,
    "balance": 79433,
    "reference": "0012258582744",
    "wallet": "09055033688",
    "duty": "jahn",
    "num": 233,
    "id": 109634,
    "note": ""
  },
  {
    "type": "RECEIVE",
    "datetime": "2023-09-24 08:37 PM",
    "amount": 200,
    "name": "RU*****E AN***W D.",
    "mobile": "09929252258",
    "msg": "6897",
    "balance": 80529,
    "reference": "9012258588914",
    "wallet": "09055033688",
    "duty": "jahn",
    "num": 232,
    "id": "109641",
    "note": ""
  },
  {
    "type": "RECEIVE",
    "datetime": "2023-09-24 08:38 PM",
    "amount": 350,
    "name": "JA™S A.",
    "mobile": "09150914411",
    "msg": "1453",
    "balance": 80872,
    "reference": "0012258592694",
    "wallet": "09055033688",
    "duty": "jahn",
    "num": 231,
    "id": 109636,
    "note": ""
  },
  {
    "type": "RECEIVE",
    "datetime": "2023-09-24 08:38 PM",
    "amount": 200,
    "name": "RU***L C.",
    "mobile": "09603818662",
    "msg": null,
    "balance": 81079,
    "reference": "4012258593066",
    "wallet": "09055033688",
    "duty": "jahn",
    "num": 230,
    "id": 109638,
    "note": ""
  },
  {
    "type": "RECEIVE",
    "datetime": "2023-09-24 08:38 PM",
    "amount": 104,
    "name": "JA*E WA***N J* M.",
    "mobile": "09303248816",
    "msg": null,
    "balance": 81183,
    "reference": "8012258601074",
    "wallet": "09055033688",
    "duty": "jahn",
    "num": 229,
    "id": 109643,
    "note": ""
  },
  {
    "type": "RECEIVE",
    "datetime": "2023-09-24 08:38 PM",
    "amount": 200,
    "name": "JA**Y T.",
    "mobile": "09513413517",
    "msg": "chas in",
    "balance": 81383,
    "reference": "7012258603746",
    "wallet": "09055033688",
    "duty": "jahn",
    "num": 228,
    "id": 109631,
    "note": ""
  },
  {
    "type": "RECEIVE",
    "datetime": "2023-09-24 08:38 PM",
    "amount": 200,
    "name": "JE****Y A.",
    "mobile": "09273908389",
    "msg": null,
    "balance": 81583,
    "reference": "0012258604170",
    "wallet": "09055033688",
    "duty": "jahn",
    "num": 227,
    "id": 109611,
    "note": ""
  },
  {
    "type": "RECEIVE",
    "datetime": "2023-09-24 08:41 PM",
    "amount": 200,
    "name": "RI**Y A.",
    "mobile": "09101737174",
    "msg": null,
    "balance": 81783,
    "reference": "0012258651730",
    "wallet": "09055033688",
    "duty": "jahn",
    "num": 226,
    "id": 109541,
    "note": ""
  },
  {
    "type": "RECEIVE",
    "datetime": "2023-09-24 08:37 PM",
    "amount": 100,
    "name": "JE**N P.",
    "mobile": "09655368824",
    "msg": "pay",
    "balance": 80329,
    "reference": "6012258587490",
    "wallet": "09055033688",
    "duty": "jahn",
    "num": 225,
    "id": 109640,
    "note": ""
  },
  {
    "type": "RECEIVE",
    "datetime": "2023-09-24 08:37 PM",
    "amount": 300,
    "name": "RO*™*L B.",
    "mobile": "09062123408",
    "msg": "cash in to pa bilis para mka bawi ako",
    "balance": 79833,
    "reference": "7012258585525",
    "wallet": "09055033688",
    "duty": "jahn",
    "num": 224,
    "id": 109626,
    "note": ""
  },
  {
    "type": "RECEIVE",
    "datetime": "2023-09-24 08:37 PM",
    "amount": 100,
    "name": "DA™*E R.",
    "mobile": "09060331073",
    "msg": null,
    "balance": 79533,
    "reference": "4012258585365",
    "wallet": "09055033688",
    "duty": "jahn",
    "num": 223,
    "id": 109629,
    "note": ""
  },
  {
    "type": "RECEIVE",
    "datetime": "2023-09-24 08:37 PM",
    "amount": 396,
    "name": "CE***R DO****N O.",
    "mobile": "09916771413",
    "msg": null,
    "balance": 80229,
    "reference": "0012258587224",
    "wallet": "09055033688",
    "duty": "jahn",
    "num": 222,
    "id": 109554,
    "note": ""
  },
  {
    "type": "RECEIVE",
    "datetime": "2023-09-24 08:37 PM",
    "amount": 1000,
    "name": "DE**A B.",
    "mobile": "09664599446",
    "msg": null,
    "balance": 78833,
    "reference": "0012258577298",
    "wallet": "09055033688",
    "duty": "jahn",
    "num": 221,
    "id": 109633,
    "note": ""
  },
  {
    "type": "RECEIVE",
    "datetime": "2023-09-24 08:37 PM",
    "amount": 100,
    "name": "CH******N LL™*D D.",
    "mobile": "09477162088",
    "msg": "8432",
    "balance": 77833,
    "reference": "5012258576681",
    "wallet": "09055033688",
    "duty": "jahn",
    "num": 220,
    "id": 109623,
    "note": ""
  },
  {
    "type": "RECEIVE",
    "datetime": "2023-09-24 08:37 PM",
    "amount": 150,
    "name": "DA***N P.",
    "mobile": "09608960420",
    "msg": null,
    "balance": 77733,
    "reference": "1012258574159",
    "wallet": "09055033688",
    "duty": "jahn",
    "num": 219,
    "id": 109635,
    "note": ""
  },
  {
    "type": "RECEIVE",
    "datetime": "2023-09-24 08:37 PM",
    "amount": 100,
    "name": "CO*****O D.",
    "mobile": "09484354345",
    "msg": null,
    "balance": 77483,
    "reference": "1012258571934",
    "wallet": "09055033688",
    "duty": "jahn",
    "num": 218,
    "id": 109617,
    "note": ""
  },
  {
    "type": "RECEIVE",
    "datetime": "2023-09-24 08:37 PM",
    "amount": 100,
    "name": "MA**™*C D.",
    "mobile": "09501389261",
    "msg": "3637",
    "balance": 77583,
    "reference": "2012258572429",
    "wallet": "09055033688",
    "duty": "jahn",
    "num": 217,
    "id": 109614,
    "note": ""
  },
  {
    "type": "RECEIVE",
    "datetime": "2023-09-24 08:36 PM",
    "amount": 140,
    "name": "PE**L AN*™**E L.",
    "mobile": "09319194179",
    "msg": "9146",
    "balance": 76133,
    "reference": "0012258565547",
    "wallet": "09055033688",
    "duty": "jahn",
    "num": 216,
    "id": 109620,
    "note": ""
  },
  {
    "type": "RECEIVE",
    "datetime": "2023-09-24 08:37 PM",
    "amount": 1000,
    "name": "NU********M B.",
    "mobile": "09276215761",
    "msg": "nur william t benito ",
    "balance": 77383,
    "reference": "5012258571779",
    "wallet": "09055033688",
    "duty": "jahn",
    "num": 215,
    "id": 109582,
    "note": ""
  },
  {
    "type": "RECEIVE",
    "datetime": "2023-09-24 08:37 PM",
    "amount": 500,
    "name": "RO**E D.",
    "mobile": "09474158240",
    "msg": null,
    "balance": 79333,
    "reference": "1012258581395",
    "wallet": "09055033688",
    "duty": "jahn",
    "num": 214,
    "id": 109637,
    "note": ""
  },
  {
    "type": "RECEIVE",
    "datetime": "2023-09-24 08:37 PM",
    "amount": 250,
    "name": "JO*N AN****Y G.",
    "mobile": "09175242479",
    "msg": null,
    "balance": 76383,
    "reference": "1012258571583",
    "wallet": "09055033688",
    "duty": "jahn",
    "num": 213,
    "id": 109627,
    "note": ""
  },
  {
    "type": "RECEIVE",
    "datetime": "2023-09-24 08:36 PM",
    "amount": 100,
    "name": "LA*****E A.",
    "mobile": "09123102813",
    "msg": null,
    "balance": 75993,
    "reference": "3012258564988",
    "wallet": "09055033688",
    "duty": "jahn",
    "num": 212,
    "id": 109609,
    "note": ""
  },
  {
    "type": "RECEIVE",
    "datetime": "2023-09-24 08:36 PM",
    "amount": 200,
    "name": "RU*Y B.",
    "mobile": "09562532961",
    "msg": null,
    "balance": 75893,
    "reference": "8012258563534",
    "wallet": "09055033688",
    "duty": "jahn",
    "num": 211,
    "id": 109601,
    "note": ""
  },
  {
    "type": "RECEIVE",
    "datetime": "2023-09-24 08:36 PM",
    "amount": 200,
    "name": "MO*****G C.",
    "mobile": "09488287116",
    "msg": "2512",
    "balance": 75693,
    "reference": "9012258563281",
    "wallet": "09055033688",
    "duty": "jahn",
    "num": 210,
    "id": 109610,
    "note": ""
  },
  {
    "type": "RECEIVE",
    "datetime": "2023-09-24 08:36 PM",
    "amount": 500,
    "name": "MA*K. AN****Y D.",
    "mobile": "09162750305",
    "msg": "city",
    "balance": 75493,
    "reference": "7012258557311",
    "wallet": "09055033688",
    "duty": "jahn",
    "num": 209,
    "id": "",
    "note": "no_request"
  },
  {
    "type": "RECEIVE",
    "datetime": "2023-09-24 08:36 PM",
    "amount": 1000,
    "name": "GL*N JO*N JU**O G.",
    "mobile": "09272941860",
    "msg": null,
    "balance": 74993,
    "reference": "3012258554703",
    "wallet": "09055033688",
    "duty": "jahn",
    "num": 208,
    "id": 109605,
    "note": ""
  },
  {
    "type": "RECEIVE",
    "datetime": "2023-09-24 08:36 PM",
    "amount": 200,
    "name": "RA*™*T S.",
    "mobile": "09473056692",
    "msg": null,
    "balance": 73993,
    "reference": "3012258552942",
    "wallet": "09055033688",
    "duty": "jahn",
    "num": 207,
    "id": 109602,
    "note": ""
  },
  {
    "type": "RECEIVE",
    "datetime": "2023-09-24 08:35 PM",
    "amount": 100,
    "name": "NE*L CH******N L.",
    "mobile": "09473634947",
    "msg": "5359",
    "balance": 73793,
    "reference": "5012258550965",
    "wallet": "09055033688",
    "duty": "jahn",
    "num": 206,
    "id": 109592,
    "note": ""
  },
  {
    "type": "RECEIVE",
    "datetime": "2023-09-24 08:35 PM",
    "amount": 100,
    "name": "EM****N G.",
    "mobile": "09970928310",
    "msg": null,
    "balance": 73693,
    "reference": "9012258550146",
    "wallet": "09055033688",
    "duty": "jahn",
    "num": 205,
    "id": 109599,
    "note": ""
  },
  {
    "type": "RECEIVE",
    "datetime": "2023-09-24 08:35 PM",
    "amount": 495,
    "name": "MA****L R.",
    "mobile": "09292483149",
    "msg": "3855",
    "balance": 73593,
    "reference": "7012258550015",
    "wallet": "09055033688",
    "duty": "jahn",
    "num": 204,
    "id": 109606,
    "note": ""
  },
  {
    "type": "RECEIVE",
    "datetime": "2023-09-24 08:35 PM",
    "amount": 500,
    "name": "BI**Y J** R.",
    "mobile": "09661456831",
    "msg": null,
    "balance": 73098,
    "reference": "0012258545803",
    "wallet": "09055033688",
    "duty": "jahn",
    "num": 203,
    "id": 109596,
    "note": ""
  },
  {
    "type": "RECEIVE",
    "datetime": "2023-09-24 08:35 PM",
    "amount": 100,
    "name": "CH******N G.",
    "mobile": "09070685960",
    "msg": null,
    "balance": 72598,
    "reference": "7012258537568",
    "wallet": "09055033688",
    "duty": "jahn",
    "num": 202,
    "id": 109547,
    "note": ""
  },
  {
    "type": "RECEIVE",
    "datetime": "2023-09-24 08:35 PM",
    "amount": 300,
    "name": "JO*N PA***K G.",
    "mobile": "09479811539",
    "msg": "1928",
    "balance": 72498,
    "reference": "0012258536576",
    "wallet": "09055033688",
    "duty": "jahn",
    "num": 201,
    "id": 109597,
    "note": ""
  },
  {
    "type": "RECEIVE",
    "datetime": "2023-09-24 08:34 PM",
    "amount": 100,
    "name": "FE“****O J.",
    "mobile": "09235818955",
    "msg": null,
    "balance": 72198,
    "reference": "6012258528788",
    "wallet": "09055033688",
    "duty": "jahn",
    "num": 200,
    "id": 109586,
    "note": ""
  },
  {
    "type": "RECEIVE",
    "datetime": "2023-09-24 08:34 PM",
    "amount": 100,
    "name": "EL**R J* A.",
    "mobile": "09267767993",
    "msg": null,
    "balance": 72098,
    "reference": "1012258526297",
    "wallet": "09055033688",
    "duty": "jahn",
    "num": 199,
    "id": 109577,
    "note": ""
  },
  {
    "type": "RECEIVE",
    "datetime": "2023-09-24 08:34 PM",
    "amount": 100,
    "name": "BR**N B.",
    "mobile": "09486751844",
    "msg": null,
    "balance": 71498,
    "reference": "4012258516537",
    "wallet": "09055033688",
    "duty": "jahn",
    "num": 198,
    "id": 109580,
    "note": ""
  },
  {
    "type": "RECEIVE",
    "datetime": "2023-09-24 08:33 PM",
    "amount": 500,
    "name": "AR***N MA*K A.",
    "mobile": "09510471485",
    "msg": "6280",
    "balance": 71398,
    "reference": "8012258514946",
    "wallet": "09055033688",
    "duty": "jahn",
    "num": 197,
    "id": 109579,
    "note": ""
  },
  {
    "type": "RECEIVE",
    "datetime": "2023-09-24 08:33 PM",
    "amount": 100,
    "name": "LI*****O G.",
    "mobile": "09701954219",
    "msg": null,
    "balance": 68498,
    "reference": "5012258505163",
    "wallet": "09055033688",
    "duty": "jahn",
    "num": 196,
    "id": 109570,
    "note": ""
  },
  {
    "type": "RECEIVE",
    "datetime": "2023-09-24 08:33 PM",
    "amount": 100,
    "name": "AL’****B D.",
    "mobile": "09168958237",
    "msg": null,
    "balance": 67798,
    "reference": "6012258501379",
    "wallet": "09055033688",
    "duty": "jahn",
    "num": 195,
    "id": 109576,
    "note": ""
  },
  {
    "type": "RECEIVE",
    "datetime": "2023-09-24 08:34 PM",
    "amount": 500,
    "name": "AL*******O S.",
    "mobile": "09500301591",
    "msg": "6396",
    "balance": 71998,
    "reference": "5012258522843",
    "wallet": "09055033688",
    "duty": "jahn",
    "num": 194,
    "id": 109583,
    "note": ""
  },
  {
    "type": "RECEIVE",
    "datetime": "2023-09-24 08:33 PM",
    "amount": 500,
    "name": "ED***D D.",
    "mobile": "09123368132",
    "msg": null,
    "balance": 68398,
    "reference": "7012258504336",
    "wallet": "09055033688",
    "duty": "jahn",
    "num": 193,
    "id": 109564,
    "note": ""
  },
  {
    "type": "RECEIVE",
    "datetime": "2023-09-24 08:33 PM",
    "amount": 100,
    "name": "MA*K JA**N R.",
    "mobile": "09482810569",
    "msg": "1931",
    "balance": 67898,
    "reference": "0012258502331",
    "wallet": "09055033688",
    "duty": "jahn",
    "num": 192,
    "id": 109569,
    "note": ""
  },
  {
    "type": "RECEIVE",
    "datetime": "2023-09-24 08:33 PM",
    "amount": 1000,
    "name": "ED***N B.",
    "mobile": "09091592623",
    "msg": "6284",
    "balance": 70898,
    "reference": "6012258506879",
    "wallet": "09055033688",
    "duty": "jahn",
    "num": 191,
    "id": 109575,
    "note": ""
  },
  {
    "type": "RECEIVE",
    "datetime": "2023-09-24 08:33 PM",
    "amount": 900,
    "name": "ME***N S.",
    "mobile": "09215038115",
    "msg": null,
    "balance": 69398,
    "reference": "7012258512109",
    "wallet": "09055033688",
    "duty": "jahn",
    "num": 190,
    "id": 109573,
    "note": ""
  },
  {
    "type": "RECEIVE",
    "datetime": "2023-09-24 08:33 PM",
    "amount": 500,
    "name": "JE****O D.",
    "mobile": "09158585825",
    "msg": null,
    "balance": 69898,
    "reference": "9012258513945",
    "wallet": "09055033688",
    "duty": "jahn",
    "num": 189,
    "id": 109574,
    "note": ""
  },
  {
    "type": "RECEIVE",
    "datetime": "2023-09-24 08:33 PM",
    "amount": 200,
    "name": "MA*C KE**Y |.",
    "mobile": "09454486619",
    "msg": "7997",
    "balance": 67698,
    "reference": "2012258499208",
    "wallet": "09055033688",
    "duty": "jahn",
    "num": 188,
    "id": 109550,
    "note": ""
  },
  {
    "type": "RECEIVE",
    "datetime": "2023-09-24 08:32 PM",
    "amount": 500,
    "name": "RO*™***K A.",
    "mobile": "09812017307",
    "msg": null,
    "balance": 67498,
    "reference": "4012258495287",
    "wallet": "09055033688",
    "duty": "jahn",
    "num": 187,
    "id": 109561,
    "note": ""
  },
  {
    "type": "RECEIVE",
    "datetime": "2023-09-24 08:32 PM",
    "amount": 100,
    "name": "JO***O P.",
    "mobile": "09167963721",
    "msg": null,
    "balance": 66998,
    "reference": "8012258489825",
    "wallet": "09055033688",
    "duty": "jahn",
    "num": 186,
    "id": 109563,
    "note": ""
  },
  {
    "type": "RECEIVE",
    "datetime": "2023-09-24 08:32 PM",
    "amount": 100,
    "name": "FE***E R.",
    "mobile": "09516713002",
    "msg": "7270",
    "balance": 66898,
    "reference": "2012258487157",
    "wallet": "09055033688",
    "duty": "jahn",
    "num": 185,
    "id": 109565,
    "note": ""
  },
  {
    "type": "RECEIVE",
    "datetime": "2023-09-24 08:32 PM",
    "amount": 100,
    "name": "JO*N ER*C P.",
    "mobile": "09569060641",
    "msg": null,
    "balance": 66798,
    "reference": "8012258486560",
    "wallet": "09055033688",
    "duty": "jahn",
    "num": 184,
    "id": 109562,
    "note": ""
  },
  {
    "type": "RECEIVE",
    "datetime": "2023-09-24 08:32 PM",
    "amount": 200,
    "name": "JO*N AL****S L.",
    "mobile": "09674190811",
    "msg": "cash in",
    "balance": 63998,
    "reference": "6012258482489",
    "wallet": "09055033688",
    "duty": "jahn",
    "num": 183,
    "id": 109559,
    "note": ""
  },
  {
    "type": "RECEIVE",
    "datetime": "2023-09-24 08:31 PM",
    "amount": 100,
    "name": "AR***E M.",
    "mobile": "09634986207",
    "msg": null,
    "balance": 61836,
    "reference": "0012258477538",
    "wallet": "09055033688",
    "duty": "jahn",
    "num": 182,
    "id": 109556,
    "note": ""
  },
  {
    "type": "RECEIVE",
    "datetime": "2023-09-24 08:32 PM",
    "amount": 500,
    "name": "SH***L U.",
    "mobile": "09553998642",
    "msg": null,
    "balance": 64498,
    "reference": "9012258482966",
    "wallet": "09055033688",
    "duty": "jahn",
    "num": 181,
    "id": 109546,
    "note": ""
  },
  {
    "type": "RECEIVE",
    "datetime": "2023-09-24 08:32 PM",
    "amount": 300,
    "name": "ES****N S.",
    "mobile": "09958165335",
    "msg": null,
    "balance": 63798,
    "reference": "4012258481327",
    "wallet": "09055033688",
    "duty": "jahn",
    "num": 180,
    "id": 109500,
    "note": ""
  },
  {
    "type": "RECEIVE",
    "datetime": "2023-09-24 08:32 PM",
    "amount": 462,
    "name": "NO“*R M.",
    "mobile": "09338100714",
    "msg": "thanks",
    "balance": 63498,
    "reference": "4012258480119",
    "wallet": "09055033688",
    "duty": "jahn",
    "num": 179,
    "id": 109549,
    "note": ""
  },
  {
    "type": "RECEIVE",
    "datetime": "2023-09-24 08:32 PM",
    "amount": 200,
    "name": "RE***L M.",
    "mobile": "09560271109",
    "msg": "8850",
    "balance": 62036,
    "reference": "6012258478101",
    "wallet": "09055033688",
    "duty": "jahn",
    "num": 178,
    "id": 109555,
    "note": ""
  },
  {
    "type": "RECEIVE",
    "datetime": "2023-09-24 08:31 PM",
    "amount": 200,
    "name": "IS****I E.",
    "mobile": "09982947119",
    "msg": null,
    "balance": 61736,
    "reference": "3012258476754",
    "wallet": "09055033688",
    "duty": "jahn",
    "num": 177,
    "id": 109543,
    "note": ""
  },
  {
    "type": "RECEIVE",
    "datetime": "2023-09-24 08:31 PM",
    "amount": 200,
    "name": "SH**A M.",
    "mobile": "09952939973",
    "msg": null,
    "balance": 61536,
    "reference": "8012258475767",
    "wallet": "09055033688",
    "duty": "jahn",
    "num": 176,
    "id": 109553,
    "note": ""
  },
  {
    "type": "RECEIVE",
    "datetime": "2023-09-24 08:32 PM",
    "amount": 2000,
    "name": "JE****Y L.",
    "mobile": "09661490210",
    "msg": null,
    "balance": 66698,
    "reference": "3012258485372",
    "wallet": "09055033688",
    "duty": "jahn",
    "num": 175,
    "id": 109571,
    "note": ""
  },
  {
    "type": "RECEIVE",
    "datetime": "2023-09-24 08:32 PM",
    "amount": 200,
    "name": "RI*****E DA*E C.",
    "mobile": "09477619681",
    "msg": null,
    "balance": 64698,
    "reference": "4012258484649",
    "wallet": "09055033688",
    "duty": "jahn",
    "num": 174,
    "id": 109560,
    "note": ""
  },
  {
    "type": "RECEIVE",
    "datetime": "2023-09-24 08:31 PM",
    "amount": 1000,
    "name": "RO***L R.",
    "mobile": "09157226565",
    "msg": null,
    "balance": 60836,
    "reference": "0012258468977",
    "wallet": "09055033688",
    "duty": "jahn",
    "num": 173,
    "id": 109551,
    "note": ""
  },
  {
    "type": "RECEIVE",
    "datetime": "2023-09-24 08:31 PM",
    "amount": 100,
    "name": "ED***D VI***R O.",
    "mobile": "09364077463",
    "msg": "8802",
    "balance": 59836,
    "reference": "1012258468061",
    "wallet": "09055033688",
    "duty": "jahn",
    "num": 172,
    "id": 109542,
    "note": ""
  },
  {
    "type": "RECEIVE",
    "datetime": "2023-09-24 08:30 PM",
    "amount": 100,
    "name": "MI*****E C.",
    "mobile": "09307060711",
    "msg": "cash in ",
    "balance": 58236,
    "reference": "4012258458184",
    "wallet": "09055033688",
    "duty": "jahn",
    "num": 171,
    "id": 109545,
    "note": ""
  },
  {
    "type": "RECEIVE",
    "datetime": "2023-09-24 08:30 PM",
    "amount": 100,
    "name": "JA**N R.",
    "mobile": "09924906286",
    "msg": "deposite betor",
    "balance": 58136,
    "reference": "2012258455760",
    "wallet": "09055033688",
    "duty": "jahn",
    "num": 170,
    "id": 109477,
    "note": ""
  },
  {
    "type": "RECEIVE",
    "datetime": "2023-09-24 08:28 PM",
    "amount": 400,
    "name": "JU**O AL“**N G.",
    "mobile": "09261982870",
    "msg": null,
    "balance": 55830,
    "reference": "6012258409493",
    "wallet": "09055033688",
    "duty": "jahn",
    "num": 169,
    "id": 109528,
    "note": ""
  },
  {
    "type": "RECEIVE",
    "datetime": "2023-09-24 08:32 PM",
    "amount": 1000,
    "name": "RO™**K J.",
    "mobile": "09569709436",
    "msg": null,
    "balance": 63036,
    "reference": "3012258479201",
    "wallet": "09055033688",
    "duty": "jahn",
    "num": 168,
    "id": 109557,
    "note": ""
  },
  {
    "type": "RECEIVE",
    "datetime": "2023-09-24 08:31 PM",
    "amount": 500,
    "name": "AL****H M.",
    "mobile": "09106210771",
    "msg": "6762",
    "balance": 58736,
    "reference": "7012258461994",
    "wallet": "09055033688",
    "duty": "jahn",
    "num": 167,
    "id": 109533,
    "note": ""
  },
  {
    "type": "RECEIVE",
    "datetime": "2023-09-24 08:31 PM",
    "amount": 1000,
    "name": "EM*****L C.",
    "mobile": "09616375179",
    "msg": null,
    "balance": 59736,
    "reference": "2012258466637",
    "wallet": "09055033688",
    "duty": "jahn",
    "num": 166,
    "id": 109544,
    "note": ""
  },
  {
    "type": "RECEIVE",
    "datetime": "2023-09-24 08:31 PM",
    "amount": 500,
    "name": "JA****E M.",
    "mobile": "09303635484",
    "msg": "talpak",
    "balance": 61336,
    "reference": "5012258472822",
    "wallet": "09055033688",
    "duty": "jahn",
    "num": 165,
    "id": 109552,
    "note": ""
  },
  {
    "type": "RECEIVE",
    "datetime": "2023-09-24 08:28 PM",
    "amount": 200,
    "name": "MA**L E.",
    "mobile": "09566979144",
    "msg": null,
    "balance": 55230,
    "reference": "5012258406271",
    "wallet": "09055033688",
    "duty": "jahn",
    "num": 164,
    "id": 109525,
    "note": ""
  },
  {
    "type": "RECEIVE",
    "datetime": "2023-09-24 08:27 PM",
    "amount": 180,
    "name": "AN*Y G.",
    "mobile": "09998322536",
    "msg": null,
    "balance": 54530,
    "reference": "9012258385000",
    "wallet": "09055033688",
    "duty": "jahn",
    "num": 163,
    "id": 109516,
    "note": ""
  },
  {
    "type": "RECEIVE",
    "datetime": "2023-09-24 08:29 PM",
    "amount": 300,
    "name": "RO***D G.",
    "mobile": "09202446044",
    "msg": null,
    "balance": 58036,
    "reference": "1012258439330",
    "wallet": "09055033688",
    "duty": "jahn",
    "num": 162,
    "id": 109540,
    "note": ""
  },
  {
    "type": "RECEIVE",
    "datetime": "2023-09-24 08:29 PM",
    "amount": 100,
    "name": "CH******A T.",
    "mobile": "09563407413",
    "msg": "8150",
    "balance": 57736,
    "reference": "4012258434513",
    "wallet": "09055033688",
    "duty": "jahn",
    "num": 161,
    "id": 109523,
    "note": ""
  },
  {
    "type": "RECEIVE",
    "datetime": "2023-09-24 08:29 PM",
    "amount": 100,
    "name": "DA™*E R.",
    "mobile": "09060331073",
    "msg": null,
    "balance": 57636,
    "reference": "4012258431190",
    "wallet": "09055033688",
    "duty": "jahn",
    "num": 160,
    "id": 109531,
    "note": ""
  },
  {
    "type": "RECEIVE",
    "datetime": "2023-09-24 08:29 PM",
    "amount": 1000,
    "name": "ED**N L.",
    "mobile": "09064180206",
    "msg": null,
    "balance": 57536,
    "reference": "7012258423840",
    "wallet": "09055033688",
    "duty": "jahn",
    "num": 159,
    "id": 109524,
    "note": ""
  },
  {
    "type": "RECEIVE",
    "datetime": "2023-09-24 08:29 PM",
    "amount": 300,
    "name": "NA***A V.",
    "mobile": "09656238339",
    "msg": "4308",
    "balance": 56536,
    "reference": "8012258422662",
    "wallet": "09055033688",
    "duty": "jahn",
    "num": 158,
    "id": 109529,
    "note": ""
  },
  {
    "type": "RECEIVE",
    "datetime": "2023-09-24 08:28 PM",
    "amount": 100,
    "name": "CH******N CR*S B.",
    "mobile": "09565495336",
    "msg": null,
    "balance": 56236,
    "reference": "9012258411668",
    "wallet": "09055033688",
    "duty": "jahn",
    "num": 157,
    "id": 109527,
    "note": ""
  },
  {
    "type": "RECEIVE",
    "datetime": "2023-09-24 08:28 PM",
    "amount": 306,
    "name": "JO*L A.",
    "mobile": "09108077660",
    "msg": "3723",
    "balance": 56136,
    "reference": "8012258409991",
    "wallet": "09055033688",
    "duty": "jahn",
    "num": 156,
    "id": 109518,
    "note": ""
  },
  {
    "type": "RECEIVE",
    "datetime": "2023-09-24 08:28 PM",
    "amount": 200,
    "name": "ER****A B.",
    "mobile": "09397646396",
    "msg": "6314",
    "balance": 55430,
    "reference": "2012258407076",
    "wallet": "09055033688",
    "duty": "jahn",
    "num": 155,
    "id": 109522,
    "note": ""
  },
  {
    "type": "RECEIVE",
    "datetime": "2023-09-24 08:27 PM",
    "amount": 500,
    "name": "AL****Z M** P.",
    "mobile": "09999127934",
    "msg": "1137",
    "balance": 55030,
    "reference": "1012258386472",
    "wallet": "09055033688",
    "duty": "jahn",
    "num": 154,
    "id": 109504,
    "note": ""
  },
  {
    "type": "RECEIVE",
    "datetime": "2023-09-24 08:26 PM",
    "amount": 200,
    "name": "WI****T C.",
    "mobile": "09154545870",
    "msg": "5746",
    "balance": 54350,
    "reference": "1012258381964",
    "wallet": "09055033688",
    "duty": "jahn",
    "num": 153,
    "id": 109502,
    "note": ""
  },
  {
    "type": "RECEIVE",
    "datetime": "2023-09-24 08:26 PM",
    "amount": 150,
    "name": "AL***N A.",
    "mobile": "09357208510",
    "msg": null,
    "balance": 54150,
    "reference": "6012258378077",
    "wallet": "09055033688",
    "duty": "jahn",
    "num": 152,
    "id": 109511,
    "note": ""
  },
  {
    "type": "RECEIVE",
    "datetime": "2023-09-24 08:26 PM",
    "amount": 200,
    "name": "VA**N CAO M.",
    "mobile": "09166757328",
    "msg": "sebvannah",
    "balance": 54000,
    "reference": "8012258372649",
    "wallet": "09055033688",
    "duty": "jahn",
    "num": 151,
    "id": 109508,
    "note": ""
  },
  {
    "type": "RECEIVE",
    "datetime": "2023-09-24 08:26 PM",
    "amount": 200,
    "name": "RU**Y E.",
    "mobile": "09638963323",
    "msg": null,
    "balance": 53800,
    "reference": "1012258371765",
    "wallet": "09055033688",
    "duty": "jahn",
    "num": 150,
    "id": 109506,
    "note": ""
  },
  {
    "type": "RECEIVE",
    "datetime": "2023-09-24 08:26 PM",
    "amount": 300,
    "name": "JO*N AN****Y G.",
    "mobile": "09175242479",
    "msg": null,
    "balance": 53600,
    "reference": "1012258365058",
    "wallet": "09055033688",
    "duty": "jahn",
    "num": 149,
    "id": 109509,
    "note": ""
  },
  {
    "type": "RECEIVE",
    "datetime": "2023-09-24 08:25 PM",
    "amount": 100,
    "name": "WV*****M JE*****N L.",
    "mobile": "09062038843",
    "msg": "5596",
    "balance": 53300,
    "reference": "5012258357447",
    "wallet": "09055033688",
    "duty": "jahn",
    "num": 148,
    "id": 109503,
    "note": ""
  },
  {
    "type": "RECEIVE",
    "datetime": "2023-09-24 08:25 PM",
    "amount": 100,
    "name": "EN*****O I* B.",
    "mobile": "09073051384",
    "msg": "account number 09073051384",
    "balance": 53300,
    "reference": "0012258357434",
    "wallet": "09055033688",
    "duty": "jahn",
    "num": 147,
    "id": 109494,
    "note": ""
  },
  {
    "type": "RECEIVE",
    "datetime": "2023-09-24 08:24 PM",
    "amount": 200,
    "name": "MI*****O R.",
    "mobile": "09519735312",
    "msg": null,
    "balance": 52100,
    "reference": "0012258341544",
    "wallet": "09055033688",
    "duty": "jahn",
    "num": 146,
    "id": 109489,
    "note": ""
  },
  {
    "type": "RECEIVE",
    "datetime": "2023-09-24 08:24 PM",
    "amount": 100,
    "name": "|** JO*D M.",
    "mobile": "09504164821",
    "msg": "cash in po clashodds",
    "balance": 51900,
    "reference": "5012258339640",
    "wallet": "09055033688",
    "duty": "jahn",
    "num": 145,
    "id": 109483,
    "note": ""
  },
  {
    "type": "RECEIVE",
    "datetime": "2023-09-24 08:24 PM",
    "amount": 100,
    "name": "RA***E M.",
    "mobile": "09497876774",
    "msg": "4853",
    "balance": 51800,
    "reference": "2012258337449",
    "wallet": "09055033688",
    "duty": "jahn",
    "num": 144,
    "id": 109488,
    "note": ""
  },
  {
    "type": "RECEIVE",
    "datetime": "2023-09-24 08:23 PM",
    "amount": 100,
    "name": "RY*N C.",
    "mobile": "09318278090",
    "msg": "sabong",
    "balance": 51155,
    "reference": "7012258319294",
    "wallet": "09055033688",
    "duty": "jahn",
    "num": 143,
    "id": 109472,
    "note": ""
  },
  {
    "type": "RECEIVE",
    "datetime": "2023-09-24 08:24 PM",
    "amount": 295,
    "name": "BI*******O J* V.",
    "mobile": "09954742628",
    "msg": null,
    "balance": 51700,
    "reference": "3012258336038",
    "wallet": "09055033688",
    "duty": "jahn",
    "num": 142,
    "id": 109484,
    "note": ""
  },
  {
    "type": "RECEIVE",
    "datetime": "2023-09-24 08:23 PM",
    "amount": 250,
    "name": "AN**W A.",
    "mobile": "09353520155",
    "msg": null,
    "balance": 51405,
    "reference": "0012258323754",
    "wallet": "09055033688",
    "duty": "jahn",
    "num": 141,
    "id": 109480,
    "note": ""
  },
  {
    "type": "RECEIVE",
    "datetime": "2023-09-24 08:23 PM",
    "amount": 150,
    "name": "ME***N R.",
    "mobile": "09988090209",
    "msg": null,
    "balance": 51055,
    "reference": "1012258311316",
    "wallet": "09055033688",
    "duty": "jahn",
    "num": 140,
    "id": 109482,
    "note": ""
  },
  {
    "type": "RECEIVE",
    "datetime": "2023-09-24 08:23 PM",
    "amount": 100,
    "name": "JU***S M.",
    "mobile": "09565387573",
    "msg": null,
    "balance": 50905,
    "reference": "6012258309404",
    "wallet": "09055033688",
    "duty": "jahn",
    "num": 139,
    "id": 109455,
    "note": ""
  },
  {
    "type": "RECEIVE",
    "datetime": "2023-09-24 08:25 PM",
    "amount": 1000,
    "name": "IR*S C.",
    "mobile": "09084231318",
    "msg": null,
    "balance": 53100,
    "reference": "9012258354699",
    "wallet": "09055033688",
    "duty": "jahn",
    "num": 138,
    "id": 109499,
    "note": ""
  },
  {
    "type": "RECEIVE",
    "datetime": "2023-09-24 08:23 PM",
    "amount": 300,
    "name": "AN****Y CH********R |.",
    "mobile": "09165355143",
    "msg": null,
    "balance": 50805,
    "reference": "7012258305695",
    "wallet": "09055033688",
    "duty": "jahn",
    "num": 137,
    "id": 109478,
    "note": ""
  },
  {
    "type": "RECEIVE",
    "datetime": "2023-09-24 08:22 PM",
    "amount": 400,
    "name": "JA***E P.",
    "mobile": "09703211344",
    "msg": null,
    "balance": 50505,
    "reference": "7012258302650",
    "wallet": "09055033688",
    "duty": "jahn",
    "num": 136,
    "id": 109469,
    "note": ""
  },
  {
    "type": "RECEIVE",
    "datetime": "2023-09-24 08:22 PM",
    "amount": 300,
    "name": "DA***S B.",
    "mobile": "09159731174",
    "msg": null,
    "balance": 50105,
    "reference": "5012258293910",
    "wallet": "09055033688",
    "duty": "jahn",
    "num": 135,
    "id": 109462,
    "note": ""
  },
  {
    "type": "RECEIVE",
    "datetime": "2023-09-24 08:22 PM",
    "amount": 115,
    "name": "MA*K LO***Z A.",
    "mobile": "09692618376",
    "msg": null,
    "balance": 49805,
    "reference": "9012258291284",
    "wallet": "09055033688",
    "duty": "jahn",
    "num": 134,
    "id": 109471,
    "note": ""
  },
  {
    "type": "RECEIVE",
    "datetime": "2023-09-24 08:21 PM",
    "amount": 100,
    "name": "CE**R B.",
    "mobile": "09073059797",
    "msg": null,
    "balance": 49490,
    "reference": "0012258280280",
    "wallet": "09055033688",
    "duty": "jahn",
    "num": 133,
    "id": 109449,
    "note": ""
  },
  {
    "type": "RECEIVE",
    "datetime": "2023-09-24 08:21 PM",
    "amount": 200,
    "name": "CH******N PA*L L.",
    "mobile": "09459701415",
    "msg": "8217",
    "balance": 49690,
    "reference": "3012258285171",
    "wallet": "09055033688",
    "duty": "jahn",
    "num": 132,
    "id": 109470,
    "note": ""
  },
  {
    "type": "RECEIVE",
    "datetime": "2023-09-24 08:21 PM",
    "amount": 280,
    "name": "FL******O S.",
    "mobile": "09125487872",
    "msg": "yt",
    "balance": 49390,
    "reference": "0012258276640",
    "wallet": "09055033688",
    "duty": "jahn",
    "num": 131,
    "id": 109450,
    "note": ""
  },
  {
    "type": "RECEIVE",
    "datetime": "2023-09-24 08:21 PM",
    "amount": 300,
    "name": "JE***R T.",
    "mobile": "09812498602",
    "msg": "5046",
    "balance": 46210,
    "reference": "5012258272011",
    "wallet": "09055033688",
    "duty": "jahn",
    "num": 130,
    "id": 109464,
    "note": ""
  },
  {
    "type": "RECEIVE",
    "datetime": "2023-09-24 08:21 PM",
    "amount": 400,
    "name": "JH*N SE***G S.",
    "mobile": "09157593985",
    "msg": null,
    "balance": 47110,
    "reference": "9012258272968",
    "wallet": "09055033688",
    "duty": "jahn",
    "num": 129,
    "id": 109458,
    "note": ""
  },
  {
    "type": "RECEIVE",
    "datetime": "2023-09-24 08:21 PM",
    "amount": 500,
    "name": "JI***- R* G.",
    "mobile": "09953664065",
    "msg": null,
    "balance": 46710,
    "reference": "1012258272745",
    "wallet": "09055033688",
    "duty": "jahn",
    "num": 128,
    "id": 109446,
    "note": ""
  },
  {
    "type": "RECEIVE",
    "datetime": "2023-09-24 08:21 PM",
    "amount": 1500,
    "name": "HI****T A.",
    "mobile": "09567164807",
    "msg": "load sabong",
    "balance": 49110,
    "reference": "5012258276582",
    "wallet": "09055033688",
    "duty": "jahn",
    "num": 127,
    "id": 109444,
    "note": ""
  },
  {
    "type": "RECEIVE",
    "datetime": "2023-09-24 08:21 PM",
    "amount": 500,
    "name": "ME***N H.",
    "mobile": "09263047058",
    "msg": null,
    "balance": 47610,
    "reference": "9012258275305",
    "wallet": "09055033688",
    "duty": "jahn",
    "num": 126,
    "id": 109466,
    "note": ""
  },
  {
    "type": "RECEIVE",
    "datetime": "2023-09-24 08:21 PM",
    "amount": 200,
    "name": "CZ*R BE*****T H.",
    "mobile": "09203692420",
    "msg": null,
    "balance": 45910,
    "reference": "9012258268429",
    "wallet": "09055033688",
    "duty": "jahn",
    "num": 125,
    "id": 109448,
    "note": ""
  },
  {
    "type": "RECEIVE",
    "datetime": "2023-09-24 08:21 PM",
    "amount": 150,
    "name": "DA***N P.",
    "mobile": "09608960420",
    "msg": null,
    "balance": 45710,
    "reference": "1012258266385",
    "wallet": "09055033688",
    "duty": "jahn",
    "num": 124,
    "id": 109463,
    "note": ""
  },
  {
    "type": "RECEIVE",
    "datetime": "2023-09-24 08:20 PM",
    "amount": 200,
    "name": "NI****E L.",
    "mobile": "09289431859",
    "msg": null,
    "balance": 45560,
    "reference": "6012258264636",
    "wallet": "09055033688",
    "duty": "jahn",
    "num": 123,
    "id": 109442,
    "note": ""
  },
  {
    "type": "RECEIVE",
    "datetime": "2023-09-24 08:20 PM",
    "amount": 300,
    "name": "AL***N DO***C P.",
    "mobile": "09983531269",
    "msg": null,
    "balance": 45360,
    "reference": "8012258263252",
    "wallet": "09055033688",
    "duty": "jahn",
    "num": 122,
    "id": 109457,
    "note": ""
  },
  {
    "type": "RECEIVE",
    "datetime": "2023-09-24 08:20 PM",
    "amount": 200,
    "name": "TE*****A A.",
    "mobile": "09071416683",
    "msg": null,
    "balance": 45060,
    "reference": "0012258262731",
    "wallet": "09055033688",
    "duty": "jahn",
    "num": 121,
    "id": 109447,
    "note": ""
  },
  {
    "type": "RECEIVE",
    "datetime": "2023-09-24 08:20 PM",
    "amount": 100,
    "name": "LO**E Z.",
    "mobile": "09283081474",
    "msg": null,
    "balance": 43860,
    "reference": "4012258261799",
    "wallet": "09055033688",
    "duty": "jahn",
    "num": 120,
    "id": 109454,
    "note": ""
  },
  {
    "type": "RECEIVE",
    "datetime": "2023-09-24 08:20 PM",
    "amount": 200,
    "name": "L** N.",
    "mobile": "09398578929",
    "msg": null,
    "balance": 43760,
    "reference": "0012258260147",
    "wallet": "09055033688",
    "duty": "jahn",
    "num": 119,
    "id": 109445,
    "note": ""
  },
  {
    "type": "RECEIVE",
    "datetime": "2023-09-24 08:20 PM",
    "amount": 200,
    "name": "RO*™L H.",
    "mobile": "09566033599",
    "msg": null,
    "balance": 43160,
    "reference": "6012258253693",
    "wallet": "09055033688",
    "duty": "jahn",
    "num": 118,
    "id": 109435,
    "note": ""
  },
  {
    "type": "RECEIVE",
    "datetime": "2023-09-24 08:19 PM",
    "amount": 100,
    "name": "DO****C O.",
    "mobile": "09235204516",
    "msg": "cash in",
    "balance": 40660,
    "reference": "5012258243996",
    "wallet": "09055033688",
    "duty": "jahn",
    "num": 117,
    "id": 109434,
    "note": ""
  },
  {
    "type": "RECEIVE",
    "datetime": "2023-09-24 08:19 PM",
    "amount": 200,
    "name": "DE***N J.",
    "mobile": "09916495751",
    "msg": null,
    "balance": 40560,
    "reference": "5012258243434",
    "wallet": "09055033688",
    "duty": "jahn",
    "num": 116,
    "id": 109441,
    "note": ""
  },
  {
    "type": "RECEIVE",
    "datetime": "2023-09-24 08:19 PM",
    "amount": 200,
    "name": "MA™**N A.",
    "mobile": "09208199886",
    "msg": null,
    "balance": 40118,
    "reference": "4012258240769",
    "wallet": "09055033688",
    "duty": "jahn",
    "num": 115,
    "id": 109427,
    "note": ""
  },
  {
    "type": "RECEIVE",
    "datetime": "2023-09-24 08:19 PM",
    "amount": 100,
    "name": "AZ****H P.",
    "mobile": "09634511081",
    "msg": "2413",
    "balance": 37943,
    "reference": "0012258229665",
    "wallet": "09055033688",
    "duty": "jahn",
    "num": 114,
    "id": 109428,
    "note": ""
  },
  {
    "type": "RECEIVE",
    "datetime": "2023-09-24 08:18 PM",
    "amount": 100,
    "name": "AL**N F.",
    "mobile": "09603911053",
    "msg": null,
    "balance": 37843,
    "reference": "2012258227124",
    "wallet": "09055033688",
    "duty": "jahn",
    "num": 113,
    "id": 109414,
    "note": ""
  },
  {
    "type": "RECEIVE",
    "datetime": "2023-09-24 08:20 PM",
    "amount": 1000,
    "name": "GL***S R.",
    "mobile": "09123142780",
    "msg": null,
    "balance": 44860,
    "reference": "4012258262536",
    "wallet": "09055033688",
    "duty": "jahn",
    "num": 112,
    "id": "",
    "note": "no_request"
  },
  {
    "type": "RECEIVE",
    "datetime": "2023-09-24 08:19 PM",
    "amount": 242,
    "name": "KA*L BE“****K A.",
    "mobile": "09361005330",
    "msg": "8717",
    "balance": 40360,
    "reference": "3012258242608",
    "wallet": "09055033688",
    "duty": "jahn",
    "num": 111,
    "id": 109429,
    "note": ""
  },
  {
    "type": "RECEIVE",
    "datetime": "2023-09-24 08:20 PM",
    "amount": 400,
    "name": "CAA JE*N HA****E D.",
    "mobile": "09369174637",
    "msg": null,
    "balance": 43560,
    "reference": "2012258254114",
    "wallet": "09055033688",
    "duty": "jahn",
    "num": 110,
    "id": 109451,
    "note": ""
  },
  {
    "type": "RECEIVE",
    "datetime": "2023-09-24 08:19 PM",
    "amount": 1300,
    "name": "EL**R J* S.",
    "mobile": "09360746633",
    "msg": null,
    "balance": 42960,
    "reference": "8012258246789",
    "wallet": "09055033688",
    "duty": "jahn",
    "num": 109,
    "id": 109433,
    "note": ""
  },
  {
    "type": "RECEIVE",
    "datetime": "2023-09-24 08:19 PM",
    "amount": 1000,
    "name": "KE**N |.",
    "mobile": "09565221380",
    "msg": null,
    "balance": 41660,
    "reference": "4012258244532",
    "wallet": "09055033688",
    "duty": "jahn",
    "num": 108,
    "id": 109436,
    "note": ""
  },
  {
    "type": "RECEIVE",
    "datetime": "2023-09-24 08:19 PM",
    "amount": 975,
    "name": "A™* V.",
    "mobile": "09918223482",
    "msg": null,
    "balance": 39918,
    "reference": "5012258235701",
    "wallet": "09055033688",
    "duty": "jahn",
    "num": 107,
    "id": 109439,
    "note": ""
  },
  {
    "type": "RECEIVE",
    "datetime": "2023-09-24 08:19 PM",
    "amount": 1000,
    "name": "JE***E D.",
    "mobile": "09709475125",
    "msg": null,
    "balance": 38943,
    "reference": "3012258230991",
    "wallet": "09055033688",
    "duty": "jahn",
    "num": 106,
    "id": 109437,
    "note": ""
  },
  {
    "type": "RECEIVE",
    "datetime": "2023-09-24 08:18 PM",
    "amount": 100,
    "name": "JE****Y P.",
    "mobile": "09770590295",
    "msg": "rush",
    "balance": 37027,
    "reference": "6012258221811",
    "wallet": "09055033688",
    "duty": "jahn",
    "num": 105,
    "id": 109423,
    "note": ""
  },
  {
    "type": "RECEIVE",
    "datetime": "2023-09-24 08:18 PM",
    "amount": 300,
    "name": "JE***O B.",
    "mobile": "09297782800",
    "msg": "jerico balhag ",
    "balance": 37743,
    "reference": "2012258226825",
    "wallet": "09055033688",
    "duty": "jahn",
    "num": 104,
    "id": 109421,
    "note": ""
  },
  {
    "type": "RECEIVE",
    "datetime": "2023-09-24 08:18 PM",
    "amount": 316,
    "name": "BR***T C.",
    "mobile": "09690471308",
    "msg": null,
    "balance": 37443,
    "reference": "0012258225694",
    "wallet": "09055033688",
    "duty": "jahn",
    "num": 103,
    "id": 109422,
    "note": ""
  },
  {
    "type": "RECEIVE",
    "datetime": "2023-09-24 08:18 PM",
    "amount": 100,
    "name": "MA**™*C D.",
    "mobile": "09501389261",
    "msg": "6211",
    "balance": 37127,
    "reference": "2012258225293",
    "wallet": "09055033688",
    "duty": "jahn",
    "num": 102,
    "id": 109418,
    "note": ""
  },
  {
    "type": "RECEIVE",
    "datetime": "2023-09-24 08:18 PM",
    "amount": 1000,
    "name": "SH***A M** D.",
    "mobile": "09665427057",
    "msg": null,
    "balance": 36927,
    "reference": "7012258221574",
    "wallet": "09055033688",
    "duty": "jahn",
    "num": 101,
    "id": 109426,
    "note": ""
  },
  {
    "type": "RECEIVE",
    "datetime": "2023-09-24 08:18 PM",
    "amount": 200,
    "name": "MA*K KE***Y V.",
    "mobile": "09108613839",
    "msg": "cash in",
    "balance": 35927,
    "reference": "3012258220476",
    "wallet": "09055033688",
    "duty": "jahn",
    "num": 100,
    "id": 109359,
    "note": ""
  },
  {
    "type": "RECEIVE",
    "datetime": "2023-09-24 08:18 PM",
    "amount": 100,
    "name": "AR*™*L P.",
    "mobile": "09610389610",
    "msg": null,
    "balance": 35727,
    "reference": "4012258218587",
    "wallet": "09055033688",
    "duty": "jahn",
    "num": 99,
    "id": 109412,
    "note": ""
  },
  {
    "type": "RECEIVE",
    "datetime": "2023-09-24 08:17 PM",
    "amount": 100,
    "name": "AL***N R.",
    "mobile": "09917624565",
    "msg": null,
    "balance": 34427,
    "reference": "1012258205811",
    "wallet": "09055033688",
    "duty": "jahn",
    "num": 98,
    "id": 109393,
    "note": ""
  },
  {
    "type": "RECEIVE",
    "datetime": "2023-09-24 08:18 PM",
    "amount": 400,
    "name": "PA*L AN****Y N.",
    "mobile": "09772074750",
    "msg": "9102",
    "balance": 35627,
    "reference": "2012258217541",
    "wallet": "09055033688",
    "duty": "jahn",
    "num": 97,
    "id": 109424,
    "note": ""
  },
  {
    "type": "RECEIVE",
    "datetime": "2023-09-24 08:18 PM",
    "amount": 200,
    "name": "JO*N CL****N D.",
    "mobile": "09273958302",
    "msg": null,
    "balance": 35227,
    "reference": "0012258207951",
    "wallet": "09055033688",
    "duty": "jahn",
    "num": 96,
    "id": 109420,
    "note": ""
  },
  {
    "type": "RECEIVE",
    "datetime": "2023-09-24 08:17 PM",
    "amount": 600,
    "name": "NI*O DE***R G.",
    "mobile": "09306762498",
    "msg": null,
    "balance": 35027,
    "reference": "5012258205822",
    "wallet": "09055033688",
    "duty": "jahn",
    "num": 95,
    "id": 109411,
    "note": ""
  },
  {
    "type": "RECEIVE",
    "datetime": "2023-09-24 08:17 PM",
    "amount": 100,
    "name": "CH******E M** S.",
    "mobile": "09703954122",
    "msg": "3096",
    "balance": 34327,
    "reference": "1012258202033",
    "wallet": "09055033688",
    "duty": "jahn",
    "num": 94,
    "id": 109384,
    "note": ""
  },
  {
    "type": "RECEIVE",
    "datetime": "2023-09-24 08:17 PM",
    "amount": 200,
    "name": "FL*****N N.",
    "mobile": "09097740686",
    "msg": "8089",
    "balance": 34227,
    "reference": "8012258201725",
    "wallet": "09055033688",
    "duty": "jahn",
    "num": 93,
    "id": 109400,
    "note": ""
  },
  {
    "type": "RECEIVE",
    "datetime": "2023-09-24 08:17 PM",
    "amount": 100,
    "name": "FE******D B.",
    "mobile": "09614308410",
    "msg": null,
    "balance": 34027,
    "reference": "9012258195416",
    "wallet": "09055033688",
    "duty": "jahn",
    "num": 92,
    "id": 109403,
    "note": ""
  },
  {
    "type": "RECEIVE",
    "datetime": "2023-09-24 08:17 PM",
    "amount": 200,
    "name": "JO*L A.",
    "mobile": "09308180022",
    "msg": null,
    "balance": 33927,
    "reference": "5012258193502",
    "wallet": "09055033688",
    "duty": "jahn",
    "num": 91,
    "id": 109396,
    "note": ""
  },
  {
    "type": "RECEIVE",
    "datetime": "2023-09-24 08:16 PM",
    "amount": 200,
    "name": "JU****O K.",
    "mobile": "09364774041",
    "msg": null,
    "balance": 33727,
    "reference": "3012258186879",
    "wallet": "09055033688",
    "duty": "jahn",
    "num": 90,
    "id": 109405,
    "note": ""
  },
  {
    "type": "RECEIVE",
    "datetime": "2023-09-24 08:16 PM",
    "amount": 200,
    "name": "AR**N C.",
    "mobile": "09672002127",
    "msg": null,
    "balance": 33527,
    "reference": "8012258183769",
    "wallet": "09055033688",
    "duty": "jahn",
    "num": 89,
    "id": 109391,
    "note": ""
  },
  {
    "type": "RECEIVE",
    "datetime": "2023-09-24 08:16 PM",
    "amount": 150,
    "name": "AR****O N.",
    "mobile": "09203938361",
    "msg": "asharman22",
    "balance": 33327,
    "reference": "3012258182984",
    "wallet": "09055033688",
    "duty": "jahn",
    "num": 88,
    "id": 109394,
    "note": ""
  },
  {
    "type": "RECEIVE",
    "datetime": "2023-09-24 08:16 PM",
    "amount": 100,
    "name": "IR™*E R.",
    "mobile": "09504751008",
    "msg": null,
    "balance": 33177,
    "reference": "1012258181845",
    "wallet": "09055033688",
    "duty": "jahn",
    "num": 87,
    "id": 109406,
    "note": ""
  },
  {
    "type": "RECEIVE",
    "datetime": "2023-09-24 08:16 PM",
    "amount": 100,
    "name": "C** J** G.",
    "mobile": "09063361145",
    "msg": "2106",
    "balance": 33077,
    "reference": "4012258179480",
    "wallet": "09055033688",
    "duty": "jahn",
    "num": 86,
    "id": 109390,
    "note": ""
  },
  {
    "type": "RECEIVE",
    "datetime": "2023-09-24 08:16 PM",
    "amount": 200,
    "name": "JA*E EL****R A.",
    "mobile": "09955046437",
    "msg": null,
    "balance": 32977,
    "reference": "4012258176010",
    "wallet": "09055033688",
    "duty": "jahn",
    "num": 85,
    "id": 109397,
    "note": ""
  },
  {
    "type": "RECEIVE",
    "datetime": "2023-09-24 08:16 PM",
    "amount": 200,
    "name": "CE**O G.",
    "mobile": "09613767108",
    "msg": null,
    "balance": 32777,
    "reference": "5012258171881",
    "wallet": "09055033688",
    "duty": "jahn",
    "num": 84,
    "id": "",
    "note": "no_request"
  },
  {
    "type": "RECEIVE",
    "datetime": "2023-09-24 08:15 PM",
    "amount": 150,
    "name": "MA***N R* C.",
    "mobile": "09618400224",
    "msg": "5906",
    "balance": 32577,
    "reference": "3012258166262",
    "wallet": "09055033688",
    "duty": "jahn",
    "num": 83,
    "id": 109382,
    "note": ""
  },
  {
    "type": "RECEIVE",
    "datetime": "2023-09-24 08:15 PM",
    "amount": 200,
    "name": "NA**A V.",
    "mobile": "09656238339",
    "msg": "3882",
    "balance": 32427,
    "reference": "8012258164548",
    "wallet": "09055033688",
    "duty": "jahn",
    "num": 82,
    "id": 109376,
    "note": ""
  },
  {
    "type": "RECEIVE",
    "datetime": "2023-09-24 08:15 PM",
    "amount": 104,
    "name": "CH******N C.",
    "mobile": "09474974441",
    "msg": null,
    "balance": 30727,
    "reference": "7012258160727",
    "wallet": "09055033688",
    "duty": "jahn",
    "num": 81,
    "id": 109375,
    "note": ""
  },
  {
    "type": "RECEIVE",
    "datetime": "2023-09-24 08:15 PM",
    "amount": 200,
    "name": "RE***N M.",
    "mobile": "09605676071",
    "msg": null,
    "balance": 30623,
    "reference": "5012258160267",
    "wallet": "09055033688",
    "duty": "jahn",
    "num": 80,
    "id": 109380,
    "note": ""
  },
  {
    "type": "RECEIVE",
    "datetime": "2023-09-24 08:15 PM",
    "amount": 1000,
    "name": "MA*K JO***H P.",
    "mobile": "09616323435",
    "msg": "6582",
    "balance": 30223,
    "reference": "0012258153886",
    "wallet": "09055033688",
    "duty": "jahn",
    "num": 79,
    "id": 109377,
    "note": ""
  },
  {
    "type": "RECEIVE",
    "datetime": "2023-09-24 08:15 PM",
    "amount": 100,
    "name": "ME****O J* T.",
    "mobile": "09602920053",
    "msg": null,
    "balance": 29223,
    "reference": "6012258151180",
    "wallet": "09055033688",
    "duty": "jahn",
    "num": 78,
    "id": 109374,
    "note": ""
  },
  {
    "type": "RECEIVE",
    "datetime": "2023-09-24 08:14 PM",
    "amount": 100,
    "name": "AL***N A.",
    "mobile": "09357208510",
    "msg": null,
    "balance": 29123,
    "reference": "6012258148298",
    "wallet": "09055033688",
    "duty": "jahn",
    "num": 77,
    "id": 109404,
    "note": ""
  },
  {
    "type": "RECEIVE",
    "datetime": "2023-09-24 08:15 PM",
    "amount": 200,
    "name": "RA*L R.",
    "mobile": "09308875929",
    "msg": null,
    "balance": 30423,
    "reference": "7012258157456",
    "wallet": "09055033688",
    "duty": "jahn",
    "num": 76,
    "id": 109365,
    "note": ""
  },
  {
    "type": "RECEIVE",
    "datetime": "2023-09-24 08:15 PM",
    "amount": 1500,
    "name": "RO******O B.",
    "mobile": "09194461765",
    "msg": null,
    "balance": 32227,
    "reference": "5012258161443",
    "wallet": "09055033688",
    "duty": "jahn",
    "num": 75,
    "id": 109371,
    "note": ""
  },
  {
    "type": "RECEIVE",
    "datetime": "2023-09-24 08:14 PM",
    "amount": 500,
    "name": "JO**R G.",
    "mobile": "09760091699",
    "msg": "5504",
    "balance": 29023,
    "reference": "7012258147972",
    "wallet": "09055033688",
    "duty": "jahn",
    "num": 74,
    "id": 109357,
    "note": ""
  },
  {
    "type": "RECEIVE",
    "datetime": "2023-09-24 08:14 PM",
    "amount": 500,
    "name": "PA**O J* M.",
    "mobile": "09291965559",
    "msg": null,
    "balance": 28523,
    "reference": "2012258143380",
    "wallet": "09055033688",
    "duty": "jahn",
    "num": 73,
    "id": 109370,
    "note": ""
  },
  {
    "type": "RECEIVE",
    "datetime": "2023-09-24 08:14 PM",
    "amount": 500,
    "name": "EM*****L A.",
    "mobile": "09161866005",
    "msg": "5341",
    "balance": 28023,
    "reference": "0012258136316",
    "wallet": "09055033688",
    "duty": "jahn",
    "num": 72,
    "id": 109361,
    "note": ""
  },
  {
    "type": "RECEIVE",
    "datetime": "2023-09-24 08:14 PM",
    "amount": 300,
    "name": "RI***L B.",
    "mobile": "09283559160",
    "msg": null,
    "balance": 27523,
    "reference": "4012258135372",
    "wallet": "09055033688",
    "duty": "jahn",
    "num": 71,
    "id": 109348,
    "note": ""
  },
  {
    "type": "RECEIVE",
    "datetime": "2023-09-24 08:14 PM",
    "amount": 100,
    "name": "ED****O L.",
    "mobile": "09959529921",
    "msg": null,
    "balance": 27223,
    "reference": "1012258135150",
    "wallet": "09055033688",
    "duty": "jahn",
    "num": 70,
    "id": "",
    "note": "no_request"
  },
  {
    "type": "RECEIVE",
    "datetime": "2023-09-24 08:14 PM",
    "amount": 300,
    "name": "AL**N L.",
    "mobile": "09505101458",
    "msg": "9413",
    "balance": 27123,
    "reference": "6012258134246",
    "wallet": "09055033688",
    "duty": "jahn",
    "num": 69,
    "id": 109353,
    "note": ""
  },
  {
    "type": "RECEIVE",
    "datetime": "2023-09-24 08:14 PM",
    "amount": 200,
    "name": "AR***D S.",
    "mobile": "09278567183",
    "msg": "ci",
    "balance": 26823,
    "reference": "5012258132563",
    "wallet": "09055033688",
    "duty": "jahn",
    "num": 68,
    "id": 109363,
    "note": ""
  },
  {
    "type": "RECEIVE",
    "datetime": "2023-09-24 08:13 PM",
    "amount": 110,
    "name": "RO™L C.",
    "mobile": "09260725294",
    "msg": "9329",
    "balance": 26323,
    "reference": "3012258123417",
    "wallet": "09055033688",
    "duty": "jahn",
    "num": 67,
    "id": 109346,
    "note": ""
  },
  {
    "type": "RECEIVE",
    "datetime": "2023-09-24 08:14 PM",
    "amount": 300,
    "name": "AN****N B.",
    "mobile": "09177851465",
    "msg": "7793",
    "balance": 26623,
    "reference": "5012258129501",
    "wallet": "09055033688",
    "duty": "jahn",
    "num": 66,
    "id": 109351,
    "note": ""
  },
  {
    "type": "RECEIVE",
    "datetime": "2023-09-24 08:13 PM",
    "amount": 150,
    "name": "WV*****M JE*****N L.",
    "mobile": "09062038843",
    "msg": "6662",
    "balance": 26213,
    "reference": "5012258122555",
    "wallet": "09055033688",
    "duty": "jahn",
    "num": 65,
    "id": 109354,
    "note": ""
  },
  {
    "type": "RECEIVE",
    "datetime": "2023-09-24 08:13 PM",
    "amount": 110,
    "name": "PA****O J* D.",
    "mobile": "09515519673",
    "msg": "6847",
    "balance": 26063,
    "reference": "3012258111282",
    "wallet": "09055033688",
    "duty": "jahn",
    "num": 64,
    "id": 109338,
    "note": ""
  },
  {
    "type": "RECEIVE",
    "datetime": "2023-09-24 08:13 PM",
    "amount": 999,
    "name": "JU***T B.",
    "mobile": "09502361070",
    "msg": "sana manalo naman ",
    "balance": 25953,
    "reference": "1012258110957",
    "wallet": "09055033688",
    "duty": "jahn",
    "num": 63,
    "id": 109342,
    "note": ""
  },
  {
    "type": "RECEIVE",
    "datetime": "2023-09-24 08:13 PM",
    "amount": 200,
    "name": "PA**O L.",
    "mobile": "09567261029",
    "msg": null,
    "balance": 24954,
    "reference": "1012258109534",
    "wallet": "09055033688",
    "duty": "jahn",
    "num": 62,
    "id": 109340,
    "note": ""
  },
  {
    "type": "RECEIVE",
    "datetime": "2023-09-24 08:12 PM",
    "amount": 100,
    "name": "JE****N T.",
    "mobile": "09756362206",
    "msg": "5126",
    "balance": 24754,
    "reference": "2012258107104",
    "wallet": "09055033688",
    "duty": "jahn",
    "num": 61,
    "id": 109316,
    "note": ""
  },
  {
    "type": "RECEIVE",
    "datetime": "2023-09-24 08:12 PM",
    "amount": 100,
    "name": "JO**. JO*N L.",
    "mobile": "09776420795",
    "msg": null,
    "balance": 24654,
    "reference": "7012258106686",
    "wallet": "09055033688",
    "duty": "jahn",
    "num": 60,
    "id": 109337,
    "note": ""
  },
  {
    "type": "RECEIVE",
    "datetime": "2023-09-24 08:12 PM",
    "amount": 100,
    "name": "GE***D VI****T E.",
    "mobile": "09070218293",
    "msg": "7622",
    "balance": 24554,
    "reference": "0012258103213",
    "wallet": "09055033688",
    "duty": "jahn",
    "num": 59,
    "id": 109329,
    "note": ""
  },
  {
    "type": "RECEIVE",
    "datetime": "2023-09-24 08:12 PM",
    "amount": 100,
    "name": "JO*N RE**N L.",
    "mobile": "09260130280",
    "msg": "8870",
    "balance": 24454,
    "reference": "9012258102098",
    "wallet": "09055033688",
    "duty": "jahn",
    "num": 58,
    "id": 109336,
    "note": ""
  },
  {
    "type": "RECEIVE",
    "datetime": "2023-09-24 08:12 PM",
    "amount": 100,
    "name": "DA*Y M** R.",
    "mobile": "09615830704",
    "msg": null,
    "balance": 24354,
    "reference": "4012258101491",
    "wallet": "09055033688",
    "duty": "jahn",
    "num": 57,
    "id": 109328,
    "note": ""
  },
  {
    "type": "RECEIVE",
    "datetime": "2023-09-24 08:12 PM",
    "amount": 300,
    "name": "MH*N RO**C |.",
    "mobile": "09062328761",
    "msg": null,
    "balance": 24254,
    "reference": "6012258097222",
    "wallet": "09055033688",
    "duty": "jahn",
    "num": 56,
    "id": 109324,
    "note": ""
  },
  {
    "type": "RECEIVE",
    "datetime": "2023-09-24 08:12 PM",
    "amount": 200,
    "name": "GR*****O B.",
    "mobile": "09669402750",
    "msg": null,
    "balance": 23954,
    "reference": "1012258096542",
    "wallet": "09055033688",
    "duty": "jahn",
    "num": 55,
    "id": 109309,
    "note": ""
  },
  {
    "type": "RECEIVE",
    "datetime": "2023-09-24 08:12 PM",
    "amount": 100,
    "name": "JE*****R S.",
    "mobile": "09517287620",
    "msg": "1868",
    "balance": 23754,
    "reference": "1012258095194",
    "wallet": "09055033688",
    "duty": "jahn",
    "num": 54,
    "id": 109314,
    "note": ""
  },
  {
    "type": "RECEIVE",
    "datetime": "2023-09-24 08:11 PM",
    "amount": 100,
    "name": "GI*O J.",
    "mobile": "09174116311",
    "msg": "1103",
    "balance": 23654,
    "reference": "2012258087159",
    "wallet": "09055033688",
    "duty": "jahn",
    "num": 53,
    "id": 109318,
    "note": ""
  },
  {
    "type": "RECEIVE",
    "datetime": "2023-09-24 08:11 PM",
    "amount": 200,
    "name": "IM*E C.",
    "mobile": "09666892587",
    "msg": null,
    "balance": 23554,
    "reference": "3012258084657",
    "wallet": "09055033688",
    "duty": "jahn",
    "num": 52,
    "id": 109298,
    "note": ""
  },
  {
    "type": "RECEIVE",
    "datetime": "2023-09-24 08:11 PM",
    "amount": 200,
    "name": "ED***N A.",
    "mobile": "09398693371",
    "msg": "6841",
    "balance": 23354,
    "reference": "6012258082812",
    "wallet": "09055033688",
    "duty": "jahn",
    "num": 51,
    "id": 109310,
    "note": ""
  },
  {
    "type": "RECEIVE",
    "datetime": "2023-09-24 08:11 PM",
    "amount": 300,
    "name": "CH****Y C.",
    "mobile": "09178751560",
    "msg": "8569",
    "balance": 23154,
    "reference": "5012258081878",
    "wallet": "09055033688",
    "duty": "jahn",
    "num": 50,
    "id": 109317,
    "note": ""
  },
  {
    "type": "RECEIVE",
    "datetime": "2023-09-24 08:11 PM",
    "amount": 100,
    "name": "JE**N P.",
    "mobile": "09655368824",
    "msg": "pay",
    "balance": 22854,
    "reference": "6012258080981",
    "wallet": "09055033688",
    "duty": "jahn",
    "num": 49,
    "id": 109315,
    "note": ""
  },
  {
    "type": "RECEIVE",
    "datetime": "2023-09-24 08:11 PM",
    "amount": 100,
    "name": "AR**N M.",
    "mobile": "09604294401",
    "msg": null,
    "balance": 19554,
    "reference": "6012258073502",
    "wallet": "09055033688",
    "duty": "jahn",
    "num": 48,
    "id": 109312,
    "note": ""
  },
  {
    "type": "RECEIVE",
    "datetime": "2023-09-24 08:11 PM",
    "amount": 300,
    "name": "LO****Y F.",
    "mobile": "09477170860",
    "msg": "9637",
    "balance": 19854,
    "reference": "4012258076580",
    "wallet": "09055033688",
    "duty": "jahn",
    "num": 47,
    "id": 109307,
    "note": ""
  },
  {
    "type": "RECEIVE",
    "datetime": "2023-09-24 08:11 PM",
    "amount": 900,
    "name": "MA**O RO*E VI***R P.",
    "mobile": "09287234774",
    "msg": null,
    "balance": 20754,
    "reference": "9012258078488",
    "wallet": "09055033688",
    "duty": "jahn",
    "num": 46,
    "id": 109308,
    "note": ""
  },
  {
    "type": "RECEIVE",
    "datetime": "2023-09-24 08:11 PM",
    "amount": 2000,
    "name": "JH*N V** |.",
    "mobile": "09757131193",
    "msg": null,
    "balance": 22754,
    "reference": "1012258080937",
    "wallet": "09055033688",
    "duty": "jahn",
    "num": 45,
    "id": 109325,
    "note": ""
  },
  {
    "type": "RECEIVE",
    "datetime": "2023-09-24 08:10 PM",
    "amount": 200,
    "name": "MA*K JAN R.",
    "mobile": "09482810569",
    "msg": "8823",
    "balance": 19454,
    "reference": "0012258063171",
    "wallet": "09055033688",
    "duty": "jahn",
    "num": 44,
    "id": 109297,
    "note": ""
  },
  {
    "type": "RECEIVE",
    "datetime": "2023-09-24 08:10 PM",
    "amount": 400,
    "name": "RY*N R.",
    "mobile": "09052884913",
    "msg": null,
    "balance": 19254,
    "reference": "2012258060861",
    "wallet": "09055033688",
    "duty": "jahn",
    "num": 43,
    "id": 109301,
    "note": ""
  },
  {
    "type": "RECEIVE",
    "datetime": "2023-09-24 08:10 PM",
    "amount": 300,
    "name": "RO*™*L P.",
    "mobile": "09851626748",
    "msg": null,
    "balance": 18854,
    "reference": "0012258043777",
    "wallet": "09055033688",
    "duty": "jahn",
    "num": 42,
    "id": 109285,
    "note": ""
  },
  {
    "type": "RECEIVE",
    "datetime": "2023-09-24 08:10 PM",
    "amount": 100,
    "name": "MA*K KE***N R.",
    "mobile": "09755571358",
    "msg": null,
    "balance": 18554,
    "reference": "8012258057749",
    "wallet": "09055033688",
    "duty": "jahn",
    "num": 41,
    "id": 109302,
    "note": ""
  },
  {
    "type": "RECEIVE",
    "datetime": "2023-09-24 08:10 PM",
    "amount": 100,
    "name": "RO****O F.",
    "mobile": "09455495484",
    "msg": "ty",
    "balance": 18454,
    "reference": "8012258055828",
    "wallet": "09055033688",
    "duty": "jahn",
    "num": 40,
    "id": 109304,
    "note": ""
  },
  {
    "type": "RECEIVE",
    "datetime": "2023-09-24 08:10 PM",
    "amount": 270,
    "name": "AR*™*L P.",
    "mobile": "09357016930",
    "msg": null,
    "balance": 18354,
    "reference": "5012258053436",
    "wallet": "09055033688",
    "duty": "jahn",
    "num": 39,
    "id": 109300,
    "note": ""
  },
  {
    "type": "RECEIVE",
    "datetime": "2023-09-24 08:10 PM",
    "amount": 1380,
    "name": "PA*L AN***W B.",
    "mobile": "09278764750",
    "msg": "2485",
    "balance": 18084,
    "reference": "9012258051607",
    "wallet": "09055033688",
    "duty": "jahn",
    "num": 38,
    "id": 109280,
    "note": ""
  },
  {
    "type": "RECEIVE",
    "datetime": "2023-09-24 08:10 PM",
    "amount": 300,
    "name": "RY*N CH********R N.",
    "mobile": "09107470602",
    "msg": "2453",
    "balance": 16704,
    "reference": "7012258050114",
    "wallet": "09055033688",
    "duty": "jahn",
    "num": 37,
    "id": 109283,
    "note": ""
  },
  {
    "type": "RECEIVE",
    "datetime": "2023-09-24 08:10 PM",
    "amount": 100,
    "name": "JO*N PA*L M.",
    "mobile": "09198564008",
    "msg": null,
    "balance": 16404,
    "reference": "5012258049310",
    "wallet": "09055033688",
    "duty": "jahn",
    "num": 36,
    "id": 109281,
    "note": ""
  },
  {
    "type": "RECEIVE",
    "datetime": "2023-09-24 08:09 PM",
    "amount": 356,
    "name": "AL*******K P.",
    "mobile": "09128322734",
    "msg": "5527",
    "balance": 16304,
    "reference": "2012258045084",
    "wallet": "09055033688",
    "duty": "jahn",
    "num": 35,
    "id": 109253,
    "note": ""
  },
  {
    "type": "RECEIVE",
    "datetime": "2023-09-24 08:09 PM",
    "amount": 100,
    "name": "WE*****N S.",
    "mobile": "09471442257",
    "msg": null,
    "balance": 15948,
    "reference": "6012258041426",
    "wallet": "09055033688",
    "duty": "jahn",
    "num": 34,
    "id": "",
    "note": "no_request"
  },
  {
    "type": "RECEIVE",
    "datetime": "2023-09-24 08:09 PM",
    "amount": 260,
    "name": "CH***L S.",
    "mobile": "09055874720",
    "msg": "online sabong",
    "balance": 15848,
    "reference": "5012258041264",
    "wallet": "09055033688",
    "duty": "jahn",
    "num": 33,
    "id": 109260,
    "note": ""
  },
  {
    "type": "RECEIVE",
    "datetime": "2023-09-24 08:09 PM",
    "amount": 1500,
    "name": "DA***N G.",
    "mobile": "09810934107",
    "msg": "cashin",
    "balance": 15588,
    "reference": "0012258040304",
    "wallet": "09055033688",
    "duty": "jahn",
    "num": 32,
    "id": 109284,
    "note": ""
  },
  {
    "type": "RECEIVE",
    "datetime": "2023-09-24 08:09 PM",
    "amount": 100,
    "name": "EF**N J* D.",
    "mobile": "09915813738",
    "msg": "2329",
    "balance": 14088,
    "reference": "0012258035001",
    "wallet": "09055033688",
    "duty": "jahn",
    "num": 31,
    "id": 109294,
    "note": ""
  },
  {
    "type": "RECEIVE",
    "datetime": "2023-09-24 08:09 PM",
    "amount": 300,
    "name": "M** CH********R U.",
    "mobile": "09497862082",
    "msg": null,
    "balance": 10988,
    "reference": "7012258032150",
    "wallet": "09055033688",
    "duty": "jahn",
    "num": 30,
    "id": 109288,
    "note": ""
  },
  {
    "type": "RECEIVE",
    "datetime": "2023-09-24 08:09 PM",
    "amount": 3000,
    "name": "JE*F P.",
    "mobile": "09606745715",
    "msg": null,
    "balance": 13988,
    "reference": "9012258033354",
    "wallet": "09055033688",
    "duty": "jahn",
    "num": 29,
    "id": 109293,
    "note": ""
  },
  {
    "type": "RECEIVE",
    "datetime": "2023-09-24 08:09 PM",
    "amount": 600,
    "name": "JE***L A.",
    "mobile": "09171118822",
    "msg": null,
    "balance": 10688,
    "reference": "5012258031456",
    "wallet": "09055033688",
    "duty": "jahn",
    "num": 28,
    "id": 109291,
    "note": ""
  },
  {
    "type": "RECEIVE",
    "datetime": "2023-09-24 08:08 PM",
    "amount": 150,
    "name": "FR****S V** B.",
    "mobile": "09929294107",
    "msg": "4271",
    "balance": 10088,
    "reference": "9012258029196",
    "wallet": "09055033688",
    "duty": "jahn",
    "num": 27,
    "id": 109272,
    "note": ""
  },
  {
    "type": "RECEIVE",
    "datetime": "2023-09-24 08:08 PM",
    "amount": 1000,
    "name": "PR*****S A** A.",
    "mobile": "09177024006",
    "msg": null,
    "balance": 8938,
    "reference": "4012258024527",
    "wallet": "09055033688",
    "duty": "jahn",
    "num": 26,
    "id": 109278,
    "note": ""
  },
  {
    "type": "RECEIVE",
    "datetime": "2023-09-24 08:08 PM",
    "amount": 1000,
    "name": "LI*O R.",
    "mobile": "09997744879",
    "msg": null,
    "balance": 9938,
    "reference": "1012258024569",
    "wallet": "09055033688",
    "duty": "jahn",
    "num": 25,
    "id": 109286,
    "note": ""
  },
  {
    "type": "RECEIVE",
    "datetime": "2023-09-24 08:08 PM",
    "amount": 820,
    "name": "LE****D C.",
    "mobile": "09175971701",
    "msg": null,
    "balance": 7938,
    "reference": "1012258023995",
    "wallet": "09055033688",
    "duty": "jahn",
    "num": 24,
    "id": 109277,
    "note": ""
  },
  {
    "type": "RECEIVE",
    "datetime": "2023-09-24 08:08 PM",
    "amount": 1000,
    "name": "ED***N B.",
    "mobile": "09091592623",
    "msg": "9696",
    "balance": 7018,
    "reference": "6012258022989",
    "wallet": "09055033688",
    "duty": "jahn",
    "num": 23,
    "id": 109274,
    "note": ""
  },
  {
    "type": "RECEIVE",
    "datetime": "2023-09-24 08:08 PM",
    "amount": 100,
    "name": "AR**E D.",
    "mobile": "09303980132",
    "msg": "9280",
    "balance": 7118,
    "reference": "1012258023014",
    "wallet": "09055033688",
    "duty": "jahn",
    "num": 22,
    "id": 109267,
    "note": ""
  },
  {
    "type": "RECEIVE",
    "datetime": "2023-09-24 08:08 PM",
    "amount": 300,
    "name": "|** JA*E S.",
    "mobile": "09668353670",
    "msg": null,
    "balance": 6018,
    "reference": "1012258021005",
    "wallet": "09055033688",
    "duty": "jahn",
    "num": 21,
    "id": 109279,
    "note": ""
  },
  {
    "type": "RECEIVE",
    "datetime": "2023-09-24 08:08 PM",
    "amount": 100,
    "name": "FR******O J* Q.",
    "mobile": "09669661257",
    "msg": null,
    "balance": 5718,
    "reference": "1012258019004",
    "wallet": "09055033688",
    "duty": "jahn",
    "num": 20,
    "id": 109275,
    "note": ""
  },
  {
    "type": "RECEIVE",
    "datetime": "2023-09-24 08:08 PM",
    "amount": 118,
    "name": "JO**Y RO*E C.",
    "mobile": "09063864828",
    "msg": null,
    "balance": 5618,
    "reference": "0012258018380",
    "wallet": "09055033688",
    "duty": "jahn",
    "num": 19,
    "id": 109282,
    "note": ""
  },
  {
    "type": "RECEIVE",
    "datetime": "2023-09-24 08:08 PM",
    "amount": 300,
    "name": "C J** S.",
    "mobile": "09812053142",
    "msg": null,
    "balance": 5500,
    "reference": "2012258015468",
    "wallet": "09055033688",
    "duty": "jahn",
    "num": 18,
    "id": 109262,
    "note": ""
  },
  {
    "type": "RECEIVE",
    "datetime": "2023-09-24 08:08 PM",
    "amount": 120,
    "name": "EL**E A.",
    "mobile": "09399658234",
    "msg": "6736",
    "balance": 5200,
    "reference": "0012258013572",
    "wallet": "09055033688",
    "duty": "jahn",
    "num": 17,
    "id": 109271,
    "note": ""
  },
  {
    "type": "RECEIVE",
    "datetime": "2023-09-24 08:07 PM",
    "amount": 100,
    "name": "ER****O R.",
    "mobile": "09662189566",
    "msg": "2330",
    "balance": 4580,
    "reference": "7012258006647",
    "wallet": "09055033688",
    "duty": "jahn",
    "num": 16,
    "id": 109266,
    "note": ""
  },
  {
    "type": "RECEIVE",
    "datetime": "2023-09-24 08:07 PM",
    "amount": 300,
    "name": "EU******O J* D.",
    "mobile": "09993018123",
    "msg": null,
    "balance": 4480,
    "reference": "1012258004010",
    "wallet": "09055033688",
    "duty": "jahn",
    "num": 15,
    "id": 109264,
    "note": ""
  },
  {
    "type": "RECEIVE",
    "datetime": "2023-09-24 08:07 PM",
    "amount": 300,
    "name": "MA*Y J** L.",
    "mobile": "09353863990",
    "msg": null,
    "balance": 4180,
    "reference": "5012257999084",
    "wallet": "09055033688",
    "duty": "jahn",
    "num": 14,
    "id": 109263,
    "note": ""
  },
  {
    "type": "RECEIVE",
    "datetime": "2023-09-24 08:07 PM",
    "amount": 200,
    "name": "JE*****L E.",
    "mobile": "09355957942",
    "msg": "6797",
    "balance": 3880,
    "reference": "4012257996013",
    "wallet": "09055033688",
    "duty": "jahn",
    "num": 13,
    "id": 109256,
    "note": ""
  },
  {
    "type": "RECEIVE",
    "datetime": "2023-09-24 08:07 PM",
    "amount": 100,
    "name": "JH***Y P.",
    "mobile": "09270832463",
    "msg": null,
    "balance": 3680,
    "reference": "1012257995147",
    "wallet": "09055033688",
    "duty": "jahn",
    "num": 12,
    "id": 109255,
    "note": ""
  },
  {
    "type": "RECEIVE",
    "datetime": "2023-09-24 08:07 PM",
    "amount": 500,
    "name": "MA****A SH**O M.",
    "mobile": "09772354280",
    "msg": "5600",
    "balance": 5080,
    "reference": "0012258007560",
    "wallet": "09055033688",
    "duty": "jahn",
    "num": 11,
    "id": 109270,
    "note": ""
  },
  {
    "type": "RECEIVE",
    "datetime": "2023-09-24 08:07 PM",
    "amount": 300,
    "name": "DE***S A.",
    "mobile": "09128879929",
    "msg": "1143",
    "balance": 3580,
    "reference": "3012257992344",
    "wallet": "09055033688",
    "duty": "jahn",
    "num": 10,
    "id": 109248,
    "note": ""
  },
  {
    "type": "RECEIVE",
    "datetime": "2023-09-24 08:07 PM",
    "amount": 100,
    "name": "MA*K JON G.",
    "mobile": "09051648108",
    "msg": "2304",
    "balance": 2780,
    "reference": "0012257989948",
    "wallet": "09055033688",
    "duty": "jahn",
    "num": 9,
    "id": 109252,
    "note": ""
  },
  {
    "type": "RECEIVE",
    "datetime": "2023-09-24 08:06 PM",
    "amount": 200,
    "name": "RO*™*L R.",
    "mobile": "09158625445",
    "msg": null,
    "balance": 2400,
    "reference": "1012257980773",
    "wallet": "09055033688",
    "duty": "jahn",
    "num": 8,
    "id": 109247,
    "note": ""
  },
  {
    "type": "RECEIVE",
    "datetime": "2023-09-24 08:06 PM",
    "amount": 600,
    "name": "WE*****N P.",
    "mobile": "09157422415",
    "msg": null,
    "balance": 2100,
    "reference": "5012257976296",
    "wallet": "09055033688",
    "duty": "jahn",
    "num": 7,
    "id": 109246,
    "note": ""
  },
  {
    "type": "RECEIVE",
    "datetime": "2023-09-24 08:07 PM",
    "amount": 100,
    "name": "JAB B.",
    "mobile": "09279892429",
    "msg": "1088",
    "balance": 2880,
    "reference": "2012257991816",
    "wallet": "09055033688",
    "duty": "jahn",
    "num": 6,
    "id": 109257,
    "note": ""
  },
  {
    "type": "RECEIVE",
    "datetime": "2023-09-24 08:07 PM",
    "amount": 400,
    "name": "RO*™*L C.",
    "mobile": "09109635660",
    "msg": "4399",
    "balance": 3280,
    "reference": "9012257992069",
    "wallet": "09055033688",
    "duty": "jahn",
    "num": 5,
    "id": 109259,
    "note": ""
  },
  {
    "type": "RECEIVE",
    "datetime": "2023-09-24 08:06 PM",
    "amount": 280,
    "name": "ST***N BA™*Y A.",
    "mobile": "09566357436",
    "msg": "9803",
    "balance": 2680,
    "reference": "4012257981934",
    "wallet": "09055033688",
    "duty": "jahn",
    "num": 4,
    "id": 109242,
    "note": ""
  },
  {
    "type": "RECEIVE",
    "datetime": "2023-09-24 08:06 PM",
    "amount": 100,
    "name": "RE™*E O.",
    "mobile": "09453076335",
    "msg": null,
    "balance": 2200,
    "reference": "1012257977312",
    "wallet": "09055033688",
    "duty": "jahn",
    "num": 3,
    "id": 109244,
    "note": ""
  },
  {
    "type": "RECEIVE",
    "datetime": "2023-09-24 08:06 PM",
    "amount": 1000,
    "name": "MI****L D.",
    "mobile": "09053281211",
    "msg": null,
    "balance": 1500,
    "reference": "3012257970104",
    "wallet": "09055033688",
    "duty": "jahn",
    "num": 2,
    "id": 109243,
    "note": ""
  },
  {
    "type": "RECEIVE",
    "datetime": "2023-09-24 08:05 PM",
    "amount": 500,
    "name": "DE**A B.",
    "mobile": "09664599446",
    "msg": null,
    "balance": 500,
    "reference": "0012257965146",
    "wallet": "09055033688",
    "duty": "jahn",
    "num": 1,
    "id": 109240,
    "note": ""
  }
]