[
  {
    "type": "RECEIVE",
    "datetime": "2023-09-23 03:02 PM",
    "amount": 1000,
    "name": "JO***A S.",
    "mobile": "09269317506",
    "msg": null,
    "balance": 102236,
    "reference": "1012232347320",
    "wallet": "09454873101",
    "duty": "cheesecake",
    "num": 128,
    "id": 103159,
    "note": ""
  },
  {
    "type": "RECEIVE",
    "datetime": "2023-09-23 02:59 PM",
    "amount": 2000,
    "name": "ALN B.",
    "mobile": "09750166162",
    "msg": null,
    "balance": 101236,
    "reference": "5012232296339",
    "wallet": "09454873101",
    "duty": "cheesecake",
    "num": 127,
    "id": 103157,
    "note": ""
  },
  {
    "type": "RECEIVE",
    "datetime": "2023-09-23 02:57 PM",
    "amount": 200,
    "name": "JU***Y S.",
    "mobile": "09919431725",
    "msg": null,
    "balance": 99236,
    "reference": "6012232251547",
    "wallet": "09454873101",
    "duty": "cheesecake",
    "num": 126,
    "id": 103195,
    "note": ""
  },
  {
    "type": "RECEIVE",
    "datetime": "2023-09-23 02:55 PM",
    "amount": 100,
    "name": "RA**Y T.",
    "mobile": "09750942425",
    "msg": null,
    "balance": 99036,
    "reference": "7012232227680",
    "wallet": "09454873101",
    "duty": "cheesecake",
    "num": 125,
    "id": 103031,
    "note": ""
  },
  {
    "type": "RECEIVE",
    "datetime": "2023-09-23 02:55 PM",
    "amount": 150,
    "name": "CR******L V.",
    "mobile": "09677823774",
    "msg": null,
    "balance": 98936,
    "reference": "7012232226909",
    "wallet": "09454873101",
    "duty": "cheesecake",
    "num": 124,
    "id": 103232,
    "note": ""
  },
  {
    "type": "RECEIVE",
    "datetime": "2023-09-23 02:55 PM",
    "amount": 200,
    "name": "MA***O T.",
    "mobile": "09631685851",
    "msg": null,
    "balance": 98786,
    "reference": "7012232226247",
    "wallet": "09454873101",
    "duty": "cheesecake",
    "num": 123,
    "id": 103174,
    "note": ""
  },
  {
    "type": "RECEIVE",
    "datetime": "2023-09-23 02:55 PM",
    "amount": 100,
    "name": "JO**N PA****K Y.",
    "mobile": "09451331775",
    "msg": null,
    "balance": 98586,
    "reference": "0012232216160",
    "wallet": "09454873101",
    "duty": "cheesecake",
    "num": 122,
    "id": 103214,
    "note": ""
  },
  {
    "type": "RECEIVE",
    "datetime": "2023-09-23 02:55 PM",
    "amount": 100,
    "name": "JE****L B.",
    "mobile": "09305501654",
    "msg": null,
    "balance": 98486,
    "reference": "5012232215877",
    "wallet": "09454873101",
    "duty": "cheesecake",
    "num": 121,
    "id": 103225,
    "note": ""
  },
  {
    "type": "RECEIVE",
    "datetime": "2023-09-23 02:54 PM",
    "amount": 500,
    "name": "RA***L A.",
    "mobile": "09164514520",
    "msg": "ci",
    "balance": 98386,
    "reference": "5012232204700",
    "wallet": "09454873101",
    "duty": "cheesecake",
    "num": 120,
    "id": 103220,
    "note": ""
  },
  {
    "type": "RECEIVE",
    "datetime": "2023-09-23 02:54 PM",
    "amount": 500,
    "name": "RA**N A.",
    "mobile": "09668108793",
    "msg": "9514",
    "balance": 97886,
    "reference": "5012232203108",
    "wallet": "09454873101",
    "duty": "cheesecake",
    "num": 119,
    "id": 103221,
    "note": ""
  },
  {
    "type": "RECEIVE",
    "datetime": "2023-09-23 02:54 PM",
    "amount": 200,
    "name": "RE***L B.",
    "mobile": "09158995439",
    "msg": null,
    "balance": 97386,
    "reference": "4012232200981",
    "wallet": "09454873101",
    "duty": "cheesecake",
    "num": 118,
    "id": 103175,
    "note": ""
  },
  {
    "type": "RECEIVE",
    "datetime": "2023-09-23 02:54 PM",
    "amount": 495,
    "name": "IR**N L.",
    "mobile": "09664683524",
    "msg": null,
    "balance": 97186,
    "reference": "1012232200802",
    "wallet": "09454873101",
    "duty": "cheesecake",
    "num": 117,
    "id": 103227,
    "note": ""
  },
  {
    "type": "RECEIVE",
    "datetime": "2023-09-23 02:54 PM",
    "amount": 500,
    "name": "AM****O G.",
    "mobile": "09476397355",
    "msg": "8461",
    "balance": 96691,
    "reference": "2012232199914",
    "wallet": "09454873101",
    "duty": "cheesecake",
    "num": 116,
    "id": 103210,
    "note": ""
  },
  {
    "type": "RECEIVE",
    "datetime": "2023-09-23 02:54 PM",
    "amount": 100,
    "name": "MA****E A.",
    "mobile": "09663046973",
    "msg": "cashin",
    "balance": 96191,
    "reference": "7012232198081",
    "wallet": "09454873101",
    "duty": "cheesecake",
    "num": 115,
    "id": 103193,
    "note": ""
  },
  {
    "type": "RECEIVE",
    "datetime": "2023-09-23 02:54 PM",
    "amount": 500,
    "name": "JO*N R** M.",
    "mobile": "09604325758",
    "msg": "7433",
    "balance": 96091,
    "reference": "8012232197681",
    "wallet": "09454873101",
    "duty": "cheesecake",
    "num": 114,
    "id": 103228,
    "note": ""
  },
  {
    "type": "RECEIVE",
    "datetime": "2023-09-23 02:54 PM",
    "amount": 500,
    "name": "ER**N B.",
    "mobile": "09997584368",
    "msg": null,
    "balance": 95591,
    "reference": "3012232197153",
    "wallet": "09454873101",
    "duty": "cheesecake",
    "num": 113,
    "id": 103229,
    "note": ""
  },
  {
    "type": "RECEIVE",
    "datetime": "2023-09-23 02:54 PM",
    "amount": 200,
    "name": "AL**N C.",
    "mobile": "09367516037",
    "msg": "4192",
    "balance": 95091,
    "reference": "4012232196920",
    "wallet": "09454873101",
    "duty": "cheesecake",
    "num": 112,
    "id": 103212,
    "note": ""
  },
  {
    "type": "RECEIVE",
    "datetime": "2023-09-23 02:54 PM",
    "amount": 100,
    "name": "ED***K C.",
    "mobile": "09276885387",
    "msg": "6689",
    "balance": 94891,
    "reference": "1012232194353",
    "wallet": "09454873101",
    "duty": "cheesecake",
    "num": 111,
    "id": 103188,
    "note": ""
  },
  {
    "type": "RECEIVE",
    "datetime": "2023-09-23 02:54 PM",
    "amount": 179,
    "name": "GE**Y G.",
    "mobile": "09958964251",
    "msg": null,
    "balance": 94791,
    "reference": "7012232193372",
    "wallet": "09454873101",
    "duty": "cheesecake",
    "num": 110,
    "id": 103176,
    "note": ""
  },
  {
    "type": "RECEIVE",
    "datetime": "2023-09-23 02:53 PM",
    "amount": 200,
    "name": "MA****A A.",
    "mobile": "09052255058",
    "msg": null,
    "balance": 94612,
    "reference": "5012232190198",
    "wallet": "09454873101",
    "duty": "cheesecake",
    "num": 109,
    "id": 103179,
    "note": ""
  },
  {
    "type": "RECEIVE",
    "datetime": "2023-09-23 02:53 PM",
    "amount": 500,
    "name": "RO**L C.",
    "mobile": "09694850381",
    "msg": null,
    "balance": 94412,
    "reference": "0012232189340",
    "wallet": "09454873101",
    "duty": "cheesecake",
    "num": 108,
    "id": 103163,
    "note": ""
  },
  {
    "type": "RECEIVE",
    "datetime": "2023-09-23 02:53 PM",
    "amount": 100,
    "name": "SE****O J* D.",
    "mobile": "09457713096",
    "msg": null,
    "balance": 93912,
    "reference": "7012232188920",
    "wallet": "09454873101",
    "duty": "cheesecake",
    "num": 107,
    "id": 103215,
    "note": ""
  },
  {
    "type": "RECEIVE",
    "datetime": "2023-09-23 02:53 PM",
    "amount": 500,
    "name": "R** JO***H M.",
    "mobile": "09151049140",
    "msg": null,
    "balance": 93812,
    "reference": "6012232188550",
    "wallet": "09454873101",
    "duty": "cheesecake",
    "num": 106,
    "id": 103216,
    "note": ""
  },
  {
    "type": "RECEIVE",
    "datetime": "2023-09-23 02:53 PM",
    "amount": 200,
    "name": "CA*L LO***E B.",
    "mobile": "09380550161",
    "msg": null,
    "balance": 93312,
    "reference": "2012232188420",
    "wallet": "09454873101",
    "duty": "cheesecake",
    "num": 105,
    "id": 103211,
    "note": ""
  },
  {
    "type": "RECEIVE",
    "datetime": "2023-09-23 02:53 PM",
    "amount": 200,
    "name": "RA***E L.",
    "mobile": "09977105576",
    "msg": null,
    "balance": 93112,
    "reference": "4012232186124",
    "wallet": "09454873101",
    "duty": "cheesecake",
    "num": 104,
    "id": 103213,
    "note": ""
  },
  {
    "type": "RECEIVE",
    "datetime": "2023-09-23 02:53 PM",
    "amount": 400,
    "name": "AR**L M.",
    "mobile": "09773912965",
    "msg": null,
    "balance": 92912,
    "reference": "6012232185693",
    "wallet": "09454873101",
    "duty": "cheesecake",
    "num": 103,
    "id": 103190,
    "note": ""
  },
  {
    "type": "RECEIVE",
    "datetime": "2023-09-23 02:53 PM",
    "amount": 270,
    "name": "EM*****L T.",
    "mobile": "09216797266",
    "msg": null,
    "balance": 92512,
    "reference": "8012232184022",
    "wallet": "09454873101",
    "duty": "cheesecake",
    "num": 102,
    "id": 103209,
    "note": ""
  },
  {
    "type": "RECEIVE",
    "datetime": "2023-09-23 02:53 PM",
    "amount": 100,
    "name": "PR******O D.",
    "mobile": "09168231135",
    "msg": "9007",
    "balance": 92242,
    "reference": "6012232183483",
    "wallet": "09454873101",
    "duty": "cheesecake",
    "num": 101,
    "id": 103192,
    "note": ""
  },
  {
    "type": "RECEIVE",
    "datetime": "2023-09-23 02:53 PM",
    "amount": 1500,
    "name": "MA***N FR****S R.",
    "mobile": "09151879227",
    "msg": null,
    "balance": 92142,
    "reference": "0012232179272",
    "wallet": "09454873101",
    "duty": "cheesecake",
    "num": 100,
    "id": 103102,
    "note": ""
  },
  {
    "type": "RECEIVE",
    "datetime": "2023-09-23 02:53 PM",
    "amount": 2000,
    "name": "JO*N PA*L A.",
    "mobile": "09463172055",
    "msg": null,
    "balance": 90642,
    "reference": "1012232172650",
    "wallet": "09454873101",
    "duty": "cheesecake",
    "num": 99,
    "id": 103126,
    "note": ""
  },
  {
    "type": "RECEIVE",
    "datetime": "2023-09-23 02:53 PM",
    "amount": 300,
    "name": "BA*Y L** A.",
    "mobile": "09951627584",
    "msg": null,
    "balance": 88642,
    "reference": "5012232178407",
    "wallet": "09454873101",
    "duty": "cheesecake",
    "num": 98,
    "id": 103182,
    "note": ""
  },
  {
    "type": "RECEIVE",
    "datetime": "2023-09-23 02:53 PM",
    "amount": 130,
    "name": "CA*****E J** V.",
    "mobile": "09669088389",
    "msg": "1022",
    "balance": 86652,
    "reference": "5012232175624",
    "wallet": "09454873101",
    "duty": "cheesecake",
    "num": 97,
    "id": 103189,
    "note": ""
  },
  {
    "type": "RECEIVE",
    "datetime": "2023-09-23 02:53 PM",
    "amount": 190,
    "name": "DE***S GL**N A.",
    "mobile": "09684026999",
    "msg": null,
    "balance": 88342,
    "reference": "9012232177376",
    "wallet": "09454873101",
    "duty": "cheesecake",
    "num": 96,
    "id": 103187,
    "note": ""
  },
  {
    "type": "RECEIVE",
    "datetime": "2023-09-23 02:53 PM",
    "amount": 1500,
    "name": "AR****O T.",
    "mobile": "09193433795",
    "msg": null,
    "balance": 88152,
    "reference": "9012232175690",
    "wallet": "09454873101",
    "duty": "cheesecake",
    "num": 95,
    "id": 103165,
    "note": ""
  },
  {
    "type": "RECEIVE",
    "datetime": "2023-09-23 02:53 PM",
    "amount": 100,
    "name": "HA***L HE****Y O.",
    "mobile": "09460859702",
    "msg": null,
    "balance": 86522,
    "reference": "3012232175268",
    "wallet": "09454873101",
    "duty": "cheesecake",
    "num": 94,
    "id": 103196,
    "note": ""
  },
  {
    "type": "RECEIVE",
    "datetime": "2023-09-23 02:53 PM",
    "amount": 200,
    "name": "WE***X B.",
    "mobile": "09632818708",
    "msg": null,
    "balance": 86422,
    "reference": "7012232174209",
    "wallet": "09454873101",
    "duty": "cheesecake",
    "num": 93,
    "id": 103134,
    "note": ""
  },
  {
    "type": "RECEIVE",
    "datetime": "2023-09-23 02:52 PM",
    "amount": 100,
    "name": "ME***N T.",
    "mobile": "09265415754",
    "msg": null,
    "balance": 86222,
    "reference": "2012232173103",
    "wallet": "09454873101",
    "duty": "cheesecake",
    "num": 92,
    "id": 103110,
    "note": ""
  },
  {
    "type": "RECEIVE",
    "datetime": "2023-09-23 02:52 PM",
    "amount": 300,
    "name": "JU***S V.",
    "mobile": "09396291291",
    "msg": null,
    "balance": 86122,
    "reference": "8012232171780",
    "wallet": "09454873101",
    "duty": "cheesecake",
    "num": 91,
    "id": 103181,
    "note": ""
  },
  {
    "type": "RECEIVE",
    "datetime": "2023-09-23 02:52 PM",
    "amount": 100,
    "name": "WA***N D.",
    "mobile": "09562316464",
    "msg": null,
    "balance": 85822,
    "reference": "8012232164793",
    "wallet": "09454873101",
    "duty": "cheesecake",
    "num": 90,
    "id": 103143,
    "note": ""
  },
  {
    "type": "RECEIVE",
    "datetime": "2023-09-23 02:52 PM",
    "amount": 1000,
    "name": "KE***E DA*E D.",
    "mobile": "09502876380",
    "msg": null,
    "balance": 85722,
    "reference": "0012232164231",
    "wallet": "09454873101",
    "duty": "cheesecake",
    "num": 89,
    "id": 103168,
    "note": ""
  },
  {
    "type": "RECEIVE",
    "datetime": "2023-09-23 02:52 PM",
    "amount": 505,
    "name": "KI*G MA*E A.",
    "mobile": "09194140265",
    "msg": null,
    "balance": 84722,
    "reference": "4012232164015",
    "wallet": "09454873101",
    "duty": "cheesecake",
    "num": 88,
    "id": 103151,
    "note": ""
  },
  {
    "type": "RECEIVE",
    "datetime": "2023-09-23 02:52 PM",
    "amount": 100,
    "name": "JU***Y A.",
    "mobile": "09122170604",
    "msg": "8622",
    "balance": null,
    "reference": "8012232157571",
    "wallet": "09454873101",
    "duty": "cheesecake",
    "num": 87,
    "id": 103128,
    "note": ""
  },
  {
    "type": "RECEIVE",
    "datetime": "2023-09-23 02:51 PM",
    "amount": 100,
    "name": "D** JA**A P.",
    "mobile": "09058251550",
    "msg": null,
    "balance": 54117,
    "reference": "3012232152461",
    "wallet": "09454873101",
    "duty": "cheesecake",
    "num": 86,
    "id": 103141,
    "note": ""
  },
  {
    "type": "RECEIVE",
    "datetime": "2023-09-23 02:52 PM",
    "amount": 30000,
    "name": "CA***E HA**L R.",
    "mobile": "09053523981",
    "msg": null,
    "balance": 84117,
    "reference": "2012232156408",
    "wallet": "09454873101",
    "duty": "cheesecake",
    "num": 85,
    "id": 103149,
    "note": ""
  },
  {
    "type": "RECEIVE",
    "datetime": "2023-09-23 02:51 PM",
    "amount": 1000,
    "name": "MI*****A S.",
    "mobile": "09652952331",
    "msg": "5832",
    "balance": 54017,
    "reference": "6012232151697",
    "wallet": "09454873101",
    "duty": "cheesecake",
    "num": 84,
    "id": 103118,
    "note": ""
  },
  {
    "type": "RECEIVE",
    "datetime": "2023-09-23 02:51 PM",
    "amount": 100,
    "name": "FR****S A.",
    "mobile": "09384612533",
    "msg": "4727",
    "balance": 53017,
    "reference": "1012232151472",
    "wallet": "09454873101",
    "duty": "cheesecake",
    "num": 83,
    "id": 103091,
    "note": ""
  },
  {
    "type": "RECEIVE",
    "datetime": "2023-09-23 02:51 PM",
    "amount": 200,
    "name": "BR****R AA*N B.",
    "mobile": "09611355733",
    "msg": null,
    "balance": 52917,
    "reference": "4012232150280",
    "wallet": "09454873101",
    "duty": "cheesecake",
    "num": 82,
    "id": 103122,
    "note": ""
  },
  {
    "type": "RECEIVE",
    "datetime": "2023-09-23 02:51 PM",
    "amount": 1000,
    "name": "JE*****N M.",
    "mobile": "09760010159",
    "msg": null,
    "balance": null,
    "reference": "6012232148477",
    "wallet": "09454873101",
    "duty": "cheesecake",
    "num": 81,
    "id": 103114,
    "note": ""
  },
  {
    "type": "RECEIVE",
    "datetime": "2023-09-23 02:51 PM",
    "amount": 100,
    "name": "ED***D C.",
    "mobile": "09465395164",
    "msg": "9543",
    "balance": null,
    "reference": "0012232147231",
    "wallet": "09454873101",
    "duty": "cheesecake",
    "num": 80,
    "id": 103108,
    "note": ""
  },
  {
    "type": "RECEIVE",
    "datetime": "2023-09-23 02:51 PM",
    "amount": 100,
    "name": "R** S.",
    "mobile": "09983371165",
    "msg": null,
    "balance": 51617,
    "reference": "0012232146770",
    "wallet": "09454873101",
    "duty": "cheesecake",
    "num": 79,
    "id": 103049,
    "note": ""
  },
  {
    "type": "RECEIVE",
    "datetime": "2023-09-23 02:51 PM",
    "amount": 100,
    "name": "CE****A V.",
    "mobile": "09075805664",
    "msg": null,
    "balance": 51517,
    "reference": "4012232145488",
    "wallet": "09454873101",
    "duty": "cheesecake",
    "num": 78,
    "id": 103116,
    "note": ""
  },
  {
    "type": "RECEIVE",
    "datetime": "2023-09-23 02:51 PM",
    "amount": 1000,
    "name": "JO*N JU****E B.",
    "mobile": "09262565899",
    "msg": "3782",
    "balance": 51417,
    "reference": "9012232144510",
    "wallet": "09454873101",
    "duty": "cheesecake",
    "num": 77,
    "id": 103100,
    "note": ""
  },
  {
    "type": "RECEIVE",
    "datetime": "2023-09-23 02:51 PM",
    "amount": 100,
    "name": "JA***N E.",
    "mobile": "09272650661",
    "msg": null,
    "balance": 50417,
    "reference": "9012232140690",
    "wallet": "09454873101",
    "duty": "cheesecake",
    "num": 76,
    "id": 103059,
    "note": ""
  },
  {
    "type": "RECEIVE",
    "datetime": "2023-09-23 02:51 PM",
    "amount": 100,
    "name": "RO***T A.",
    "mobile": "09276997096",
    "msg": "cash in",
    "balance": null,
    "reference": "5012232140511",
    "wallet": "09454873101",
    "duty": "cheesecake",
    "num": 75,
    "id": 103081,
    "note": ""
  },
  {
    "type": "RECEIVE",
    "datetime": "2023-09-23 02:51 PM",
    "amount": 100,
    "name": "EM*****L L.",
    "mobile": "09124975532",
    "msg": null,
    "balance": null,
    "reference": "7012232140209",
    "wallet": "09454873101",
    "duty": "cheesecake",
    "num": 74,
    "id": 103104,
    "note": ""
  },
  {
    "type": "RECEIVE",
    "datetime": "2023-09-23 02:51 PM",
    "amount": 100,
    "name": "JO*H B.",
    "mobile": "09365181443",
    "msg": null,
    "balance": 50117,
    "reference": "0012232139269",
    "wallet": "09454873101",
    "duty": "cheesecake",
    "num": 73,
    "id": 103086,
    "note": ""
  },
  {
    "type": "RECEIVE",
    "datetime": "2023-09-23 02:51 PM",
    "amount": 100,
    "name": "JE**N P.",
    "mobile": "09655368824",
    "msg": "pay",
    "balance": null,
    "reference": "6012232138749",
    "wallet": "09454873101",
    "duty": "cheesecake",
    "num": 72,
    "id": 103036,
    "note": ""
  },
  {
    "type": "RECEIVE",
    "datetime": "2023-09-23 02:51 PM",
    "amount": 300,
    "name": "JA****E E.",
    "mobile": "09563952125",
    "msg": "7480",
    "balance": 49917,
    "reference": "6012232138506",
    "wallet": "09454873101",
    "duty": "cheesecake",
    "num": 71,
    "id": 103089,
    "note": ""
  },
  {
    "type": "RECEIVE",
    "datetime": "2023-09-23 02:50 PM",
    "amount": 1000,
    "name": "JO******K |.",
    "mobile": "09616181092",
    "msg": null,
    "balance": 49617,
    "reference": "4012232136865",
    "wallet": "09454873101",
    "duty": "cheesecake",
    "num": 70,
    "id": 103098,
    "note": ""
  },
  {
    "type": "RECEIVE",
    "datetime": "2023-09-23 02:50 PM",
    "amount": 2000,
    "name": "JO*E MI****O P.",
    "mobile": "09151151972",
    "msg": null,
    "balance": 48617,
    "reference": "7012232132832",
    "wallet": "09454873101",
    "duty": "cheesecake",
    "num": 69,
    "id": 103094,
    "note": ""
  },
  {
    "type": "RECEIVE",
    "datetime": "2023-09-23 02:50 PM",
    "amount": 200,
    "name": "JE****Y F.",
    "mobile": "09477503732",
    "msg": null,
    "balance": 46617,
    "reference": "3012232129673",
    "wallet": "09454873101",
    "duty": "cheesecake",
    "num": 68,
    "id": 103071,
    "note": ""
  },
  {
    "type": "RECEIVE",
    "datetime": "2023-09-23 02:50 PM",
    "amount": 100,
    "name": "JO*N V.",
    "mobile": "09156813121",
    "msg": null,
    "balance": 46417,
    "reference": "9012232129241",
    "wallet": "09454873101",
    "duty": "cheesecake",
    "num": 67,
    "id": 103083,
    "note": ""
  },
  {
    "type": "RECEIVE",
    "datetime": "2023-09-23 02:50 PM",
    "amount": 100,
    "name": "MA*Y HO*E P.",
    "mobile": "09665262480",
    "msg": "7419",
    "balance": 46317,
    "reference": "7012232128515",
    "wallet": "09454873101",
    "duty": "cheesecake",
    "num": 66,
    "id": 103073,
    "note": ""
  },
  {
    "type": "RECEIVE",
    "datetime": "2023-09-23 02:50 PM",
    "amount": 3000,
    "name": "NI*O D.",
    "mobile": "09467103566",
    "msg": null,
    "balance": 46217,
    "reference": "3012232126748",
    "wallet": "09454873101",
    "duty": "cheesecake",
    "num": 65,
    "id": 103000,
    "note": ""
  },
  {
    "type": "RECEIVE",
    "datetime": "2023-09-23 02:50 PM",
    "amount": 1800,
    "name": "GL*N JO*N JU**O G.",
    "mobile": "09272941860",
    "msg": null,
    "balance": 43217,
    "reference": "3012232123868",
    "wallet": "09454873101",
    "duty": "cheesecake",
    "num": 64,
    "id": 103039,
    "note": ""
  },
  {
    "type": "RECEIVE",
    "datetime": "2023-09-23 02:50 PM",
    "amount": 4000,
    "name": "PA****K JO*E R.",
    "mobile": "09062644212",
    "msg": "6053",
    "balance": 41417,
    "reference": "3012232122960",
    "wallet": "09454873101",
    "duty": "cheesecake",
    "num": 63,
    "id": 103027,
    "note": ""
  },
  {
    "type": "RECEIVE",
    "datetime": "2023-09-23 02:50 PM",
    "amount": 600,
    "name": "MI*****A C.",
    "mobile": "09935364680",
    "msg": null,
    "balance": 37417,
    "reference": "5012232121626",
    "wallet": "09454873101",
    "duty": "cheesecake",
    "num": 62,
    "id": 103063,
    "note": ""
  },
  {
    "type": "RECEIVE",
    "datetime": "2023-09-23 02:50 PM",
    "amount": 200,
    "name": "CH******N LL**D A.",
    "mobile": "09672812223",
    "msg": null,
    "balance": 36817,
    "reference": "9012232121173",
    "wallet": "09454873101",
    "duty": "cheesecake",
    "num": 61,
    "id": 103035,
    "note": ""
  },
  {
    "type": "RECEIVE",
    "datetime": "2023-09-23 02:50 PM",
    "amount": 200,
    "name": "NI***A EL***O D.",
    "mobile": "09469495556",
    "msg": null,
    "balance": 36617,
    "reference": "7012232120946",
    "wallet": "09454873101",
    "duty": "cheesecake",
    "num": 60,
    "id": 103038,
    "note": ""
  },
  {
    "type": "RECEIVE",
    "datetime": "2023-09-23 02:49 PM",
    "amount": 100,
    "name": "GL*N MA****W D.",
    "mobile": "09957136359",
    "msg": null,
    "balance": 36417,
    "reference": "6012232118864",
    "wallet": "09454873101",
    "duty": "cheesecake",
    "num": 59,
    "id": 103043,
    "note": ""
  },
  {
    "type": "RECEIVE",
    "datetime": "2023-09-23 02:49 PM",
    "amount": 490,
    "name": "DI*****O J* B.",
    "mobile": "09503167362",
    "msg": null,
    "balance": 36317,
    "reference": "1012232118424",
    "wallet": "09454873101",
    "duty": "cheesecake",
    "num": 58,
    "id": 103053,
    "note": ""
  },
  {
    "type": "RECEIVE",
    "datetime": "2023-09-23 02:49 PM",
    "amount": 100,
    "name": "HA***. ©.",
    "mobile": "09474082195",
    "msg": null,
    "balance": null,
    "reference": "7012232117902",
    "wallet": "09454873101",
    "duty": "cheesecake",
    "num": 57,
    "id": 103045,
    "note": ""
  },
  {
    "type": "RECEIVE",
    "datetime": "2023-09-23 02:49 PM",
    "amount": 150,
    "name": "MA****L B.",
    "mobile": "09100023011",
    "msg": null,
    "balance": null,
    "reference": "6012232116645",
    "wallet": "09454873101",
    "duty": "cheesecake",
    "num": 56,
    "id": 103051,
    "note": ""
  },
  {
    "type": "RECEIVE",
    "datetime": "2023-09-23 02:49 PM",
    "amount": 100,
    "name": "AA**N JO*N G.",
    "mobile": "09158000974",
    "msg": null,
    "balance": 35577,
    "reference": "1012232111179",
    "wallet": "09454873101",
    "duty": "cheesecake",
    "num": 55,
    "id": 103029,
    "note": ""
  },
  {
    "type": "RECEIVE",
    "datetime": "2023-09-23 02:49 PM",
    "amount": 100,
    "name": "EF**N M.",
    "mobile": "09126503828",
    "msg": null,
    "balance": 35477,
    "reference": "7012232108168",
    "wallet": "09454873101",
    "duty": "cheesecake",
    "num": 54,
    "id": 102989,
    "note": ""
  },
  {
    "type": "RECEIVE",
    "datetime": "2023-09-23 02:49 PM",
    "amount": 500,
    "name": "JO*N RO***Y P.",
    "mobile": "09458500618",
    "msg": null,
    "balance": 35377,
    "reference": "7012232103303",
    "wallet": "09454873101",
    "duty": "cheesecake",
    "num": 53,
    "id": 103023,
    "note": ""
  },
  {
    "type": "RECEIVE",
    "datetime": "2023-09-23 02:49 PM",
    "amount": 309,
    "name": "ME***N A.",
    "mobile": "09565474480",
    "msg": null,
    "balance": null,
    "reference": "3012232105182",
    "wallet": "09454873101",
    "duty": "cheesecake",
    "num": 52,
    "id": 103014,
    "note": ""
  },
  {
    "type": "RECEIVE",
    "datetime": "2023-09-23 02:49 PM",
    "amount": 250,
    "name": "K** AN**L AN*******E H.",
    "mobile": "09353391654",
    "msg": null,
    "balance": 34568,
    "reference": "3012232104992",
    "wallet": "09454873101",
    "duty": "cheesecake",
    "num": 51,
    "id": 103025,
    "note": ""
  },
  {
    "type": "RECEIVE",
    "datetime": "2023-09-23 02:49 PM",
    "amount": 2000,
    "name": "DA***O J* D.",
    "mobile": "09158959037",
    "msg": "9142",
    "balance": 34318,
    "reference": "4012232103987",
    "wallet": "09454873101",
    "duty": "cheesecake",
    "num": 50,
    "id": 103011,
    "note": ""
  },
  {
    "type": "RECEIVE",
    "datetime": "2023-09-23 02:49 PM",
    "amount": 100,
    "name": "RO****O J* A.",
    "mobile": "09666642095",
    "msg": null,
    "balance": 32318,
    "reference": "8012232102350",
    "wallet": "09454873101",
    "duty": "cheesecake",
    "num": 49,
    "id": 102983,
    "note": ""
  },
  {
    "type": "RECEIVE",
    "datetime": "2023-09-23 02:48 PM",
    "amount": 300,
    "name": "HA***D L.",
    "mobile": "09952998216",
    "msg": null,
    "balance": 32218,
    "reference": "3012232100528",
    "wallet": "09454873101",
    "duty": "cheesecake",
    "num": 48,
    "id": 102988,
    "note": ""
  },
  {
    "type": "RECEIVE",
    "datetime": "2023-09-23 02:48 PM",
    "amount": 200,
    "name": "CH****R M** LO*D I.",
    "mobile": "09859544951",
    "msg": null,
    "balance": 31918,
    "reference": "3012232100068",
    "wallet": "09454873101",
    "duty": "cheesecake",
    "num": 47,
    "id": 102944,
    "note": ""
  },
  {
    "type": "RECEIVE",
    "datetime": "2023-09-23 02:48 PM",
    "amount": 1500,
    "name": "LU*******A G.",
    "mobile": "09672438011",
    "msg": null,
    "balance": 31718,
    "reference": "6012232099790",
    "wallet": "09454873101",
    "duty": "cheesecake",
    "num": 46,
    "id": 103021,
    "note": ""
  },
  {
    "type": "RECEIVE",
    "datetime": "2023-09-23 02:48 PM",
    "amount": 150,
    "name": "NE***N J.",
    "mobile": "09459850950",
    "msg": null,
    "balance": 30218,
    "reference": "2012232098168",
    "wallet": "09454873101",
    "duty": "cheesecake",
    "num": 45,
    "id": 102972,
    "note": ""
  },
  {
    "type": "RECEIVE",
    "datetime": "2023-09-23 02:48 PM",
    "amount": 125,
    "name": "EM*****L S.",
    "mobile": "09770121033",
    "msg": null,
    "balance": 29928,
    "reference": "7012232093622",
    "wallet": "09454873101",
    "duty": "cheesecake",
    "num": 44,
    "id": 102979,
    "note": ""
  },
  {
    "type": "RECEIVE",
    "datetime": "2023-09-23 02:48 PM",
    "amount": 140,
    "name": "GE****S E.",
    "mobile": "09050445420",
    "msg": null,
    "balance": 30068,
    "reference": "0012232093722",
    "wallet": "09454873101",
    "duty": "cheesecake",
    "num": 43,
    "id": 103009,
    "note": ""
  },
  {
    "type": "RECEIVE",
    "datetime": "2023-09-23 02:48 PM",
    "amount": 500,
    "name": "RA**Y M.",
    "mobile": "09668003417",
    "msg": null,
    "balance": 29803,
    "reference": "6012232093294",
    "wallet": "09454873101",
    "duty": "cheesecake",
    "num": 42,
    "id": 103006,
    "note": ""
  },
  {
    "type": "RECEIVE",
    "datetime": "2023-09-23 02:48 PM",
    "amount": 233,
    "name": "T** PA****K D.",
    "mobile": "09669125963",
    "msg": null,
    "balance": 29303,
    "reference": "3012232093268",
    "wallet": "09454873101",
    "duty": "cheesecake",
    "num": 41,
    "id": 102997,
    "note": ""
  },
  {
    "type": "RECEIVE",
    "datetime": "2023-09-23 02:48 PM",
    "amount": 100,
    "name": "CR*****O C.",
    "mobile": "09751903192",
    "msg": "c",
    "balance": 29070,
    "reference": "5012232093187",
    "wallet": "09454873101",
    "duty": "cheesecake",
    "num": 40,
    "id": 102981,
    "note": ""
  },
  {
    "type": "RECEIVE",
    "datetime": "2023-09-23 02:48 PM",
    "amount": 150,
    "name": "AL****R JO*N C.",
    "mobile": "09858480899",
    "msg": null,
    "balance": 28970,
    "reference": "2012232092746",
    "wallet": "09454873101",
    "duty": "cheesecake",
    "num": 39,
    "id": 102993,
    "note": ""
  },
  {
    "type": "RECEIVE",
    "datetime": "2023-09-23 02:48 PM",
    "amount": 200,
    "name": "SH*****N NL*T Y** FE**R C.",
    "mobile": "09351155026",
    "msg": null,
    "balance": 28820,
    "reference": "4012232091453",
    "wallet": "09454873101",
    "duty": "cheesecake",
    "num": 38,
    "id": 102953,
    "note": ""
  },
  {
    "type": "RECEIVE",
    "datetime": "2023-09-23 02:48 PM",
    "amount": 2000,
    "name": "ALN B.",
    "mobile": "09750166162",
    "msg": null,
    "balance": 28620,
    "reference": "5012232090704",
    "wallet": "09454873101",
    "duty": "cheesecake",
    "num": 37,
    "id": 102946,
    "note": ""
  },
  {
    "type": "RECEIVE",
    "datetime": "2023-09-23 02:48 PM",
    "amount": 500,
    "name": "RI**Y A.",
    "mobile": "09454400585",
    "msg": null,
    "balance": 26620,
    "reference": "9012232088613",
    "wallet": "09454873101",
    "duty": "cheesecake",
    "num": 36,
    "id": 102995,
    "note": ""
  },
  {
    "type": "RECEIVE",
    "datetime": "2023-09-23 02:48 PM",
    "amount": 415,
    "name": "JE****E B.",
    "mobile": "09053554491",
    "msg": null,
    "balance": 26120,
    "reference": "2012232085862",
    "wallet": "09454873101",
    "duty": "cheesecake",
    "num": 35,
    "id": 102964,
    "note": ""
  },
  {
    "type": "RECEIVE",
    "datetime": "2023-09-23 02:48 PM",
    "amount": 200,
    "name": "LO**A M.",
    "mobile": "09194102147",
    "msg": "8210",
    "balance": 25705,
    "reference": "0012232084327",
    "wallet": "09454873101",
    "duty": "cheesecake",
    "num": 34,
    "id": 102960,
    "note": ""
  },
  {
    "type": "RECEIVE",
    "datetime": "2023-09-23 02:48 PM",
    "amount": 100,
    "name": "MI****L F.",
    "mobile": "09273208500",
    "msg": "4966",
    "balance": 25505,
    "reference": "8012232083916",
    "wallet": "09454873101",
    "duty": "cheesecake",
    "num": 33,
    "id": 102970,
    "note": ""
  },
  {
    "type": "RECEIVE",
    "datetime": "2023-09-23 02:48 PM",
    "amount": 100,
    "name": "DA***N P.",
    "mobile": "09511464849",
    "msg": "2838",
    "balance": 25405,
    "reference": "4012232083551",
    "wallet": "09454873101",
    "duty": "cheesecake",
    "num": 32,
    "id": 102966,
    "note": ""
  },
  {
    "type": "RECEIVE",
    "datetime": "2023-09-23 02:47 PM",
    "amount": 250,
    "name": "MI****L I** M.",
    "mobile": "09974894723",
    "msg": null,
    "balance": 25305,
    "reference": "1012232082658",
    "wallet": "09454873101",
    "duty": "cheesecake",
    "num": 31,
    "id": 102976,
    "note": ""
  },
  {
    "type": "RECEIVE",
    "datetime": "2023-09-23 02:47 PM",
    "amount": 300,
    "name": "JO*N MA***N C.",
    "mobile": "09357913741",
    "msg": null,
    "balance": 25055,
    "reference": "2012232078442",
    "wallet": "09454873101",
    "duty": "cheesecake",
    "num": 30,
    "id": 102904,
    "note": ""
  },
  {
    "type": "RECEIVE",
    "datetime": "2023-09-23 02:47 PM",
    "amount": 300,
    "name": "JO*N KR*******R V.",
    "mobile": "09453721955",
    "msg": "5411",
    "balance": 24755,
    "reference": "0012232076593",
    "wallet": "09454873101",
    "duty": "cheesecake",
    "num": 29,
    "id": 102950,
    "note": ""
  },
  {
    "type": "RECEIVE",
    "datetime": "2023-09-23 02:47 PM",
    "amount": 100,
    "name": "R** D.",
    "mobile": "09982631130",
    "msg": "1783",
    "balance": 24455,
    "reference": "5012232076403",
    "wallet": "09454873101",
    "duty": "cheesecake",
    "num": 28,
    "id": 102943,
    "note": ""
  },
  {
    "type": "RECEIVE",
    "datetime": "2023-09-23 02:47 PM",
    "amount": 150,
    "name": "RO***D Q@.",
    "mobile": "09708161216",
    "msg": "cash in",
    "balance": 24355,
    "reference": "3012232075966",
    "wallet": "09454873101",
    "duty": "cheesecake",
    "num": 27,
    "id": 102941,
    "note": ""
  },
  {
    "type": "RECEIVE",
    "datetime": "2023-09-23 02:47 PM",
    "amount": 100,
    "name": "DI****R R.",
    "mobile": "09122247192",
    "msg": null,
    "balance": 24205,
    "reference": "8012232073523",
    "wallet": "09454873101",
    "duty": "cheesecake",
    "num": 26,
    "id": 102956,
    "note": ""
  },
  {
    "type": "RECEIVE",
    "datetime": "2023-09-23 02:47 PM",
    "amount": 305,
    "name": "JO***H P.",
    "mobile": "09685344739",
    "msg": null,
    "balance": 24105,
    "reference": "9012232073060",
    "wallet": "09454873101",
    "duty": "cheesecake",
    "num": 25,
    "id": 102934,
    "note": ""
  },
  {
    "type": "RECEIVE",
    "datetime": "2023-09-23 02:47 PM",
    "amount": 300,
    "name": "AN*****E A.",
    "mobile": "09491045270",
    "msg": "cash in",
    "balance": 23800,
    "reference": "6012232072687",
    "wallet": "09454873101",
    "duty": "cheesecake",
    "num": 24,
    "id": 102933,
    "note": ""
  },
  {
    "type": "RECEIVE",
    "datetime": "2023-09-23 02:47 PM",
    "amount": 100,
    "name": "SAY H.",
    "mobile": "09604025687",
    "msg": null,
    "balance": 23500,
    "reference": "8012232070288",
    "wallet": "09454873101",
    "duty": "cheesecake",
    "num": 23,
    "id": 102931,
    "note": ""
  },
  {
    "type": "RECEIVE",
    "datetime": "2023-09-23 02:47 PM",
    "amount": 100,
    "name": "AL**N C.",
    "mobile": "09311730132",
    "msg": null,
    "balance": 21400,
    "reference": "9012232067252",
    "wallet": "09454873101",
    "duty": "cheesecake",
    "num": 22,
    "id": 102936,
    "note": ""
  },
  {
    "type": "RECEIVE",
    "datetime": "2023-09-23 02:47 PM",
    "amount": 2000,
    "name": "MA*K AN***O C.",
    "mobile": "09951943490",
    "msg": "2272",
    "balance": 23400,
    "reference": "9012232064657",
    "wallet": "09454873101",
    "duty": "cheesecake",
    "num": 21,
    "id": 102924,
    "note": ""
  },
  {
    "type": "RECEIVE",
    "datetime": "2023-09-23 02:47 PM",
    "amount": 800,
    "name": "D** JO*L R.",
    "mobile": "09496742431",
    "msg": null,
    "balance": 21300,
    "reference": "6012232066968",
    "wallet": "09454873101",
    "duty": "cheesecake",
    "num": 20,
    "id": 102926,
    "note": ""
  },
  {
    "type": "RECEIVE",
    "datetime": "2023-09-23 02:46 PM",
    "amount": 100,
    "name": "HA**L P.",
    "mobile": "09304056911",
    "msg": null,
    "balance": 19010,
    "reference": "3012232063994",
    "wallet": "09454873101",
    "duty": "cheesecake",
    "num": 19,
    "id": 102880,
    "note": ""
  },
  {
    "type": "RECEIVE",
    "datetime": "2023-09-23 02:47 PM",
    "amount": 1490,
    "name": "MA*K AN****Y N.",
    "mobile": "09463386364",
    "msg": null,
    "balance": 20500,
    "reference": "3012232066534",
    "wallet": "09454873101",
    "duty": "cheesecake",
    "num": 18,
    "id": 102894,
    "note": ""
  },
  {
    "type": "RECEIVE",
    "datetime": "2023-09-23 02:46 PM",
    "amount": 1000,
    "name": "TO**S J* C.",
    "mobile": "09664872496",
    "msg": null,
    "balance": 18910,
    "reference": "5012232062740",
    "wallet": "09454873101",
    "duty": "cheesecake",
    "num": 17,
    "id": 102930,
    "note": ""
  },
  {
    "type": "RECEIVE",
    "datetime": "2023-09-23 02:46 PM",
    "amount": 1000,
    "name": "MA*K RA****L N.",
    "mobile": "09158116551",
    "msg": null,
    "balance": 17910,
    "reference": "6012232062197",
    "wallet": "09454873101",
    "duty": "cheesecake",
    "num": 16,
    "id": 102910,
    "note": ""
  },
  {
    "type": "RECEIVE",
    "datetime": "2023-09-23 02:46 PM",
    "amount": 100,
    "name": "JO*****A A.",
    "mobile": "09560291949",
    "msg": null,
    "balance": 16910,
    "reference": "4012232061860",
    "wallet": "09454873101",
    "duty": "cheesecake",
    "num": 15,
    "id": 102921,
    "note": ""
  },
  {
    "type": "RECEIVE",
    "datetime": "2023-09-23 02:46 PM",
    "amount": 100,
    "name": "HA***D E.",
    "mobile": "09159559918",
    "msg": null,
    "balance": 16810,
    "reference": "9012232059415",
    "wallet": "09454873101",
    "duty": "cheesecake",
    "num": 14,
    "id": 102914,
    "note": ""
  },
  {
    "type": "RECEIVE",
    "datetime": "2023-09-23 02:46 PM",
    "amount": 100,
    "name": "RI*O C.",
    "mobile": "09103805760",
    "msg": null,
    "balance": 16710,
    "reference": "6012232058903",
    "wallet": "09454873101",
    "duty": "cheesecake",
    "num": 13,
    "id": 102916,
    "note": ""
  },
  {
    "type": "RECEIVE",
    "datetime": "2023-09-23 02:46 PM",
    "amount": 1000,
    "name": "RA***L JO*N B.",
    "mobile": "09667331104",
    "msg": "7439",
    "balance": 16610,
    "reference": "1012232054318",
    "wallet": "09454873101",
    "duty": "cheesecake",
    "num": 12,
    "id": 102912,
    "note": ""
  },
  {
    "type": "RECEIVE",
    "datetime": "2023-09-23 02:46 PM",
    "amount": 160,
    "name": "HA*S RO**E T.",
    "mobile": "09387756801",
    "msg": "sabong",
    "balance": 15610,
    "reference": "5012232052348",
    "wallet": "09454873101",
    "duty": "cheesecake",
    "num": 11,
    "id": 102870,
    "note": ""
  },
  {
    "type": "RECEIVE",
    "datetime": "2023-09-23 02:46 PM",
    "amount": 400,
    "name": "MA****N O.",
    "mobile": "09279266610",
    "msg": null,
    "balance": 15450,
    "reference": "7012232052126",
    "wallet": "09454873101",
    "duty": "cheesecake",
    "num": 10,
    "id": 102872,
    "note": ""
  },
  {
    "type": "RECEIVE",
    "datetime": "2023-09-23 02:46 PM",
    "amount": 3000,
    "name": "JE*****N D.",
    "mobile": "09661352102",
    "msg": "4873",
    "balance": 15050,
    "reference": "7012232051162",
    "wallet": "09454873101",
    "duty": "cheesecake",
    "num": 9,
    "id": 102868,
    "note": ""
  },
  {
    "type": "RECEIVE",
    "datetime": "2023-09-23 02:46 PM",
    "amount": 250,
    "name": "GE***D S.",
    "mobile": "09452104733",
    "msg": null,
    "balance": 12050,
    "reference": "2012232050338",
    "wallet": "09454873101",
    "duty": "cheesecake",
    "num": 8,
    "id": 102895,
    "note": ""
  },
  {
    "type": "RECEIVE",
    "datetime": "2023-09-23 02:46 PM",
    "amount": 400,
    "name": "RE****D P.",
    "mobile": "09069125136",
    "msg": null,
    "balance": 11800,
    "reference": "7012232049157",
    "wallet": "09454873101",
    "duty": "cheesecake",
    "num": 7,
    "id": 102888,
    "note": ""
  },
  {
    "type": "RECEIVE",
    "datetime": "2023-09-23 02:46 PM",
    "amount": 100,
    "name": "LA**E JU*Y G.",
    "mobile": "09273888848",
    "msg": null,
    "balance": 11300,
    "reference": "8012232047460",
    "wallet": "09454873101",
    "duty": "cheesecake",
    "num": 6,
    "id": 102898,
    "note": ""
  },
  {
    "type": "RECEIVE",
    "datetime": "2023-09-23 02:46 PM",
    "amount": 100,
    "name": "CR******E M.",
    "mobile": "09358604909",
    "msg": null,
    "balance": 11400,
    "reference": "6012232047733",
    "wallet": "09454873101",
    "duty": "cheesecake",
    "num": 5,
    "id": 102874,
    "note": ""
  },
  {
    "type": "RECEIVE",
    "datetime": "2023-09-23 02:45 PM",
    "amount": 300,
    "name": "JEN G.",
    "mobile": "09150471408",
    "msg": "2636",
    "balance": 11200,
    "reference": "3012232045393",
    "wallet": "09454873101",
    "duty": "cheesecake",
    "num": 4,
    "id": "",
    "note": "no_request"
  },
  {
    "type": "RECEIVE",
    "datetime": "2023-09-23 02:45 PM",
    "amount": 500,
    "name": "PR***E GU****R J.",
    "mobile": "09954753602",
    "msg": "4177",
    "balance": 10900,
    "reference": "2012232045279",
    "wallet": "09454873101",
    "duty": "cheesecake",
    "num": 3,
    "id": 102878,
    "note": ""
  },
  {
    "type": "RECEIVE",
    "datetime": "2023-09-23 02:45 PM",
    "amount": 400,
    "name": "LU****O F.",
    "mobile": "09953822746",
    "msg": "cash in",
    "balance": 10400,
    "reference": "1012232036549",
    "wallet": "09454873101",
    "duty": "cheesecake",
    "num": 2,
    "id": 102864,
    "note": ""
  },
  {
    "type": "RECEIVE",
    "datetime": "2023-09-23 02:45 PM",
    "amount": 10000,
    "name": "GI****T D.",
    "mobile": "09458399612",
    "msg": null,
    "balance": 10000,
    "reference": "9012232034196",
    "wallet": "09454873101",
    "duty": "cheesecake",
    "num": 1,
    "id": 102866,
    "note": ""
  }
]